{
  "generated_at": "2026-03-11T12:41:34.170000+00:00",
  "windows": {
    "train_start": "2026-01-07T10:00:00+00:00",
    "train_end_exclusive": "2026-02-05T10:00:00+00:00",
    "val_start": "2026-02-05T10:00:00+00:00",
    "val_end_exclusive": "2026-02-18T10:00:00+00:00",
    "requested_oos_end_exclusive": "2026-03-07T10:00:00.001000+00:00",
    "actual_oos_end_exclusive": "2026-03-07T10:00:00.001000+00:00",
    "actual_max_timestamp": "2026-03-07T10:00:00+00:00"
  },
  "execution_profile": {
    "requested_symbols": [
      "BTC/USDT",
      "XAU/USDT",
      "XAG/USDT"
    ],
    "requested_timeframes_raw": [
      "4h"
    ],
    "requested_timeframes": [
      "4h"
    ],
    "low_ram_profile": true,
    "allow_metals": true,
    "custom_windows": true
  },
  "eligible_symbols": [
    "BTC/USDT",
    "XAU/USDT",
    "XAG/USDT"
  ],
  "excluded_symbols": [],
  "coverage": [
    {
      "symbol": "BTC/USDT",
      "coverage_start": "2026-01-07T10:00:00+00:00",
      "coverage_end": "2026-03-07T10:00:00+00:00",
      "full_start_coverage": true,
      "requested_oos_end": "2026-03-07T10:00:00.001000+00:00"
    },
    {
      "symbol": "XAU/USDT",
      "coverage_start": "2026-01-07T10:00:00+00:00",
      "coverage_end": "2026-03-07T10:00:00+00:00",
      "full_start_coverage": true,
      "requested_oos_end": "2026-03-07T10:00:00.001000+00:00"
    },
    {
      "symbol": "XAG/USDT",
      "coverage_start": "2026-01-07T10:00:00+00:00",
      "coverage_end": "2026-03-07T10:00:00+00:00",
      "full_start_coverage": true,
      "requested_oos_end": "2026-03-07T10:00:00.001000+00:00"
    }
  ],
  "candidate_count": 6,
  "evaluated_count": 6,
  "promoted_count": 0,
  "btc_beating_candidate_count": 0,
  "three_month_two_pct_candidate_count": 0,
  "provisional_candidate_count": 0,
  "candidate_pool_count": 0,
  "best_per_strategy": [
    {
      "candidate_id": "pair_spread_4h_balanced_btcusdt_xauusdt_1.8_0.45",
      "name": "pair_spread_4h_balanced_btcusdt_xauusdt_1.8_0.45",
      "strategy_class": "PairSpreadZScoreStrategy",
      "family": "market_neutral",
      "strategy_timeframe": "4h",
      "symbols": [
        "BTC/USDT",
        "XAU/USDT"
      ],
      "params": {
        "lookback_window": 96,
        "hedge_window": 192,
        "entry_z": 1.8,
        "exit_z": 0.45,
        "stop_z": 3.4,
        "max_hold_bars": 120,
        "min_correlation": 0.08,
        "cooldown_bars": 5,
        "reentry_z_buffer": 0.18,
        "stop_loss_pct": 0.025,
        "symbol_x": "BTC/USDT",
        "symbol_y": "XAU/USDT"
      },
      "notes": "Mixed-pair 4h probe balanced.",
      "tags": [
        "probe",
        "market_neutral",
        "pair",
        "spread",
        "zscore",
        "mixed_assets"
      ],
      "train": {
        "return": 0.0,
        "total_return": 0.0,
        "cagr": 0.0,
        "sharpe": 0.0,
        "sortino": 0.0,
        "calmar": 0.0,
        "mdd": 0.0,
        "max_drawdown": 0.0,
        "turnover": 0.0,
        "trades": 0.0,
        "trade_count": 0.0,
        "win_rate": 0.0,
        "avg_trade": 0.0,
        "exposure": 0.0,
        "volatility": 0.0,
        "stability": 0.0,
        "rolling_sharpe_min": 0.0,
        "worst_month": 0.0,
        "benchmark_corr": 0.0,
        "deflated_sharpe": 0.0,
        "pbo": 0.0,
        "spa_pvalue": 1.0
      },
      "val": {
        "return": 0.0,
        "total_return": 0.0,
        "cagr": 0.0,
        "sharpe": 0.0,
        "sortino": 0.0,
        "calmar": 0.0,
        "mdd": 0.0,
        "max_drawdown": 0.0,
        "turnover": 0.0,
        "trades": 0.0,
        "trade_count": 0.0,
        "win_rate": 0.0,
        "avg_trade": 0.0,
        "exposure": 0.0,
        "volatility": 0.0,
        "stability": 0.0,
        "rolling_sharpe_min": 0.0,
        "worst_month": 0.0,
        "benchmark_corr": 0.0,
        "deflated_sharpe": 0.0,
        "pbo": 0.0,
        "spa_pvalue": 1.0
      },
      "oos": {
        "return": 0.0,
        "total_return": 0.0,
        "cagr": 0.0,
        "sharpe": 0.0,
        "sortino": 0.0,
        "calmar": 0.0,
        "mdd": 0.0,
        "max_drawdown": 0.0,
        "turnover": 0.0,
        "trades": 0.0,
        "trade_count": 0.0,
        "win_rate": 0.0,
        "avg_trade": 0.0,
        "exposure": 0.0,
        "volatility": 0.0,
        "stability": 0.0,
        "rolling_sharpe_min": 0.0,
        "worst_month": 0.0,
        "benchmark_corr": 0.0,
        "deflated_sharpe": 0.0,
        "pbo": 0.0,
        "spa_pvalue": 1.0
      },
      "hurdle_fields": {
        "train": {
          "pass": false,
          "score": -1.0,
          "excess_return": 0.0
        },
        "val": {
          "pass": false,
          "score": -1.0,
          "excess_return": 0.0
        },
        "oos": {
          "pass": false,
          "score": -1.0,
          "excess_return": 0.0
        }
      },
      "hard_reject_reasons": {
        "oos_sharpe": 0.0,
        "trade_count": 0.0
      },
      "return_streams": {
        "train": [
          {
            "t": 1767744000000.0,
            "v": 0.0
          },
          {
            "t": 1767830400000.0,
            "v": 0.0
          },
          {
            "t": 1767916800000.0,
            "v": 0.0
          },
          {
            "t": 1768003200000.0,
            "v": 0.0
          },
          {
            "t": 1768089600000.0,
            "v": 0.0
          },
          {
            "t": 1768176000000.0,
            "v": 0.0
          },
          {
            "t": 1768262400000.0,
            "v": 0.0
          },
          {
            "t": 1768348800000.0,
            "v": 0.0
          },
          {
            "t": 1768435200000.0,
            "v": 0.0
          },
          {
            "t": 1768521600000.0,
            "v": 0.0
          },
          {
            "t": 1768608000000.0,
            "v": 0.0
          },
          {
            "t": 1768694400000.0,
            "v": 0.0
          },
          {
            "t": 1768780800000.0,
            "v": 0.0
          },
          {
            "t": 1768867200000.0,
            "v": 0.0
          },
          {
            "t": 1768953600000.0,
            "v": 0.0
          },
          {
            "t": 1769040000000.0,
            "v": 0.0
          },
          {
            "t": 1769126400000.0,
            "v": 0.0
          },
          {
            "t": 1769212800000.0,
            "v": 0.0
          },
          {
            "t": 1769299200000.0,
            "v": 0.0
          },
          {
            "t": 1769385600000.0,
            "v": 0.0
          },
          {
            "t": 1769472000000.0,
            "v": 0.0
          },
          {
            "t": 1769558400000.0,
            "v": 0.0
          },
          {
            "t": 1769644800000.0,
            "v": 0.0
          },
          {
            "t": 1769731200000.0,
            "v": 0.0
          },
          {
            "t": 1769817600000.0,
            "v": 0.0
          },
          {
            "t": 1769904000000.0,
            "v": 0.0
          },
          {
            "t": 1769990400000.0,
            "v": 0.0
          },
          {
            "t": 1770076800000.0,
            "v": 0.0
          },
          {
            "t": 1770163200000.0,
            "v": 0.0
          },
          {
            "t": 1770249600000.0,
            "v": 0.0
          }
        ],
        "val": [
          {
            "t": 1770249600000.0,
            "v": 0.0
          },
          {
            "t": 1770336000000.0,
            "v": 0.0
          },
          {
            "t": 1770422400000.0,
            "v": 0.0
          },
          {
            "t": 1770508800000.0,
            "v": 0.0
          },
          {
            "t": 1770595200000.0,
            "v": 0.0
          },
          {
            "t": 1770681600000.0,
            "v": 0.0
          },
          {
            "t": 1770768000000.0,
            "v": 0.0
          },
          {
            "t": 1770854400000.0,
            "v": 0.0
          },
          {
            "t": 1770940800000.0,
            "v": 0.0
          },
          {
            "t": 1771027200000.0,
            "v": 0.0
          },
          {
            "t": 1771113600000.0,
            "v": 0.0
          },
          {
            "t": 1771200000000.0,
            "v": 0.0
          },
          {
            "t": 1771286400000.0,
            "v": 0.0
          },
          {
            "t": 1771372800000.0,
            "v": 0.0
          }
        ],
        "oos": [
          {
            "t": 1771372800000.0,
            "v": 0.0
          },
          {
            "t": 1771459200000.0,
            "v": 0.0
          },
          {
            "t": 1771545600000.0,
            "v": 0.0
          },
          {
            "t": 1771632000000.0,
            "v": 0.0
          },
          {
            "t": 1771718400000.0,
            "v": 0.0
          },
          {
            "t": 1771804800000.0,
            "v": 0.0
          },
          {
            "t": 1771891200000.0,
            "v": 0.0
          },
          {
            "t": 1771977600000.0,
            "v": 0.0
          },
          {
            "t": 1772064000000.0,
            "v": 0.0
          },
          {
            "t": 1772150400000.0,
            "v": 0.0
          },
          {
            "t": 1772236800000.0,
            "v": 0.0
          },
          {
            "t": 1772323200000.0,
            "v": 0.0
          },
          {
            "t": 1772409600000.0,
            "v": 0.0
          },
          {
            "t": 1772496000000.0,
            "v": 0.0
          },
          {
            "t": 1772582400000.0,
            "v": 0.0
          },
          {
            "t": 1772668800000.0,
            "v": 0.0
          },
          {
            "t": 1772755200000.0,
            "v": 0.0
          },
          {
            "t": 1772841600000.0,
            "v": 0.0
          }
        ]
      },
      "metadata": {
        "timeframe": "4h",
        "pair": "BTC/USDT_XAU/USDT",
        "pair_variant": "balanced",
        "source": "2026-03-11-mixed-pair-probe",
        "event_driven_proxy": true,
        "cost_rate": 0.0008
      },
      "validation_score": 0.0,
      "validation_monthly_hurdle": [
        {
          "month": "2026-02",
          "strategy_return": 0.0,
          "btc_buy_hold_return": -0.05113651666678476,
          "threshold": 0.02,
          "excess_vs_threshold": -0.02,
          "strict_pass": false,
          "btc_pass": true,
          "pass": false
        }
      ],
      "oos_monthly_hurdle": [
        {
          "month": "2026-02",
          "strategy_return": 0.0,
          "btc_buy_hold_return": -0.05113651666678476,
          "threshold": 0.02,
          "excess_vs_threshold": -0.02,
          "strict_pass": false,
          "btc_pass": true,
          "pass": false
        },
        {
          "month": "2026-03",
          "strategy_return": 0.0,
          "btc_buy_hold_return": 0.033972623574144434,
          "threshold": 0.033972623574144434,
          "excess_vs_threshold": -0.033972623574144434,
          "strict_pass": false,
          "btc_pass": false,
          "pass": false
        }
      ],
      "recent_three_months": [
        {
          "month": "2026-02",
          "strategy_return": 0.0,
          "btc_buy_hold_return": -0.05113651666678476,
          "threshold": 0.02,
          "excess_vs_threshold": -0.02,
          "strict_pass": false,
          "btc_pass": true,
          "pass": false
        },
        {
          "month": "2026-03",
          "strategy_return": 0.0,
          "btc_buy_hold_return": 0.033972623574144434,
          "threshold": 0.033972623574144434,
          "excess_vs_threshold": -0.033972623574144434,
          "strict_pass": false,
          "btc_pass": false,
          "pass": false
        }
      ],
      "validation_hurdle_pass": true,
      "validation_btc_hurdle_pass": true,
      "oos_btc_hurdle_pass": false,
      "recent_three_month_two_pct_pass": false,
      "promoted": false,
      "btc_beating_candidate": false,
      "three_month_two_pct_candidate": false,
      "candidate_pool_eligible": false
    }
  ],
  "portfolio": {
    "construction_basis": "best_per_strategy_fallback",
    "selection": {
      "fit_split": "val",
      "report_split": "oos",
      "selection_basis": "validation_only"
    },
    "weights": [
      {
        "candidate_id": "pair_spread_4h_balanced_btcusdt_xauusdt_1.8_0.45",
        "name": "pair_spread_4h_balanced_btcusdt_xauusdt_1.8_0.45",
        "strategy_class": "PairSpreadZScoreStrategy",
        "family": "market_neutral",
        "symbols": [
          "BTC/USDT",
          "XAU/USDT"
        ],
        "timeframe": "4h",
        "weight": 1.0,
        "basis": "best_per_strategy_fallback",
        "oos_return": 0.0,
        "oos_sharpe": 0.0
      }
    ],
    "train": {
      "total_return": 0.0,
      "cagr": 0.0,
      "sharpe": 0.0,
      "sortino": 0.0,
      "calmar": 0.0,
      "max_drawdown": 0.0,
      "volatility": 0.0
    },
    "val": {
      "total_return": 0.0,
      "cagr": 0.0,
      "sharpe": 0.0,
      "sortino": 0.0,
      "calmar": 0.0,
      "max_drawdown": 0.0,
      "volatility": 0.0
    },
    "oos": {
      "total_return": 0.0,
      "cagr": 0.0,
      "sharpe": 0.0,
      "sortino": 0.0,
      "calmar": 0.0,
      "max_drawdown": 0.0,
      "volatility": 0.0
    },
    "monthly_hurdle": [
      {
        "month": "2026-02",
        "strategy_return": 0.0,
        "btc_buy_hold_return": -0.05113651666678476,
        "threshold": 0.02,
        "excess_vs_threshold": -0.02,
        "strict_pass": false,
        "btc_pass": true,
        "pass": false
      },
      {
        "month": "2026-03",
        "strategy_return": 0.0,
        "btc_buy_hold_return": 0.033972623574144434,
        "threshold": 0.033972623574144434,
        "excess_vs_threshold": -0.033972623574144434,
        "strict_pass": false,
        "btc_pass": false,
        "pass": false
      }
    ],
    "return_streams": {
      "train": [
        {
          "t": 1767744000000,
          "v": 0.0
        },
        {
          "t": 1767830400000,
          "v": 0.0
        },
        {
          "t": 1767916800000,
          "v": 0.0
        },
        {
          "t": 1768003200000,
          "v": 0.0
        },
        {
          "t": 1768089600000,
          "v": 0.0
        },
        {
          "t": 1768176000000,
          "v": 0.0
        },
        {
          "t": 1768262400000,
          "v": 0.0
        },
        {
          "t": 1768348800000,
          "v": 0.0
        },
        {
          "t": 1768435200000,
          "v": 0.0
        },
        {
          "t": 1768521600000,
          "v": 0.0
        },
        {
          "t": 1768608000000,
          "v": 0.0
        },
        {
          "t": 1768694400000,
          "v": 0.0
        },
        {
          "t": 1768780800000,
          "v": 0.0
        },
        {
          "t": 1768867200000,
          "v": 0.0
        },
        {
          "t": 1768953600000,
          "v": 0.0
        },
        {
          "t": 1769040000000,
          "v": 0.0
        },
        {
          "t": 1769126400000,
          "v": 0.0
        },
        {
          "t": 1769212800000,
          "v": 0.0
        },
        {
          "t": 1769299200000,
          "v": 0.0
        },
        {
          "t": 1769385600000,
          "v": 0.0
        },
        {
          "t": 1769472000000,
          "v": 0.0
        },
        {
          "t": 1769558400000,
          "v": 0.0
        },
        {
          "t": 1769644800000,
          "v": 0.0
        },
        {
          "t": 1769731200000,
          "v": 0.0
        },
        {
          "t": 1769817600000,
          "v": 0.0
        },
        {
          "t": 1769904000000,
          "v": 0.0
        },
        {
          "t": 1769990400000,
          "v": 0.0
        },
        {
          "t": 1770076800000,
          "v": 0.0
        },
        {
          "t": 1770163200000,
          "v": 0.0
        },
        {
          "t": 1770249600000,
          "v": 0.0
        }
      ],
      "val": [
        {
          "t": 1770249600000,
          "v": 0.0
        },
        {
          "t": 1770336000000,
          "v": 0.0
        },
        {
          "t": 1770422400000,
          "v": 0.0
        },
        {
          "t": 1770508800000,
          "v": 0.0
        },
        {
          "t": 1770595200000,
          "v": 0.0
        },
        {
          "t": 1770681600000,
          "v": 0.0
        },
        {
          "t": 1770768000000,
          "v": 0.0
        },
        {
          "t": 1770854400000,
          "v": 0.0
        },
        {
          "t": 1770940800000,
          "v": 0.0
        },
        {
          "t": 1771027200000,
          "v": 0.0
        },
        {
          "t": 1771113600000,
          "v": 0.0
        },
        {
          "t": 1771200000000,
          "v": 0.0
        },
        {
          "t": 1771286400000,
          "v": 0.0
        },
        {
          "t": 1771372800000,
          "v": 0.0
        }
      ],
      "oos": [
        {
          "t": 1771372800000,
          "v": 0.0
        },
        {
          "t": 1771459200000,
          "v": 0.0
        },
        {
          "t": 1771545600000,
          "v": 0.0
        },
        {
          "t": 1771632000000,
          "v": 0.0
        },
        {
          "t": 1771718400000,
          "v": 0.0
        },
        {
          "t": 1771804800000,
          "v": 0.0
        },
        {
          "t": 1771891200000,
          "v": 0.0
        },
        {
          "t": 1771977600000,
          "v": 0.0
        },
        {
          "t": 1772064000000,
          "v": 0.0
        },
        {
          "t": 1772150400000,
          "v": 0.0
        },
        {
          "t": 1772236800000,
          "v": 0.0
        },
        {
          "t": 1772323200000,
          "v": 0.0
        },
        {
          "t": 1772409600000,
          "v": 0.0
        },
        {
          "t": 1772496000000,
          "v": 0.0
        },
        {
          "t": 1772582400000,
          "v": 0.0
        },
        {
          "t": 1772668800000,
          "v": 0.0
        },
        {
          "t": 1772755200000,
          "v": 0.0
        },
        {
          "t": 1772841600000,
          "v": 0.0
        }
      ]
    }
  },
  "monthly_thresholds": {
    "2026-02": {
      "btc_buy_hold_return": -0.05113651666678476,
      "threshold": 0.02
    },
    "2026-03": {
      "btc_buy_hold_return": 0.033972623574144434,
      "threshold": 0.033972623574144434
    }
  },
  "notes": {
    "local_data_gap": null,
    "low_ram_exclusions": [
      "MicroRangeExpansion1sStrategy"
    ],
    "timeframe_exclusions": [
      "1s"
    ],
    "requested_timeframes_excluded": [],
    "strict_low_ram_exclusion": true,
    "metals_allowed": true,
    "candidate_pool_policy": "Strict promoted strategies stay primary. If none are promoted, keep provisional shortlist candidates that either beat BTC on the validation month or deliver at least 2% in each of the latest three months.",
    "manual_profile": "Use a higher-timeframe/core-symbol profile when RAM is constrained; this run reports only the explicitly requested symbol/timeframe slice."
  }
}