{
  "generated_at_utc": "2026-03-07T13:08:21.900580+00:00",
  "db_path": "data/market_parquet",
  "exchange_id": "binance",
  "since_ms": null,
  "until_ms": null,
  "mark_index_interval": "1m",
  "open_interest_period": "5m",
  "force_full": false,
  "symbols": [
    {
      "symbol": "BTC/USDT",
      "status": "up_to_date",
      "ohlcv_rows": 37218931,
      "ohlcv_start_ms": 1700000000000,
      "ohlcv_end_ms": 1772877628000,
      "feature_last_ts": 1772888160000,
      "ohlcv_start_utc": "2023-11-14T22:13:20+00:00",
      "ohlcv_end_utc": "2026-03-07T10:00:28+00:00",
      "feature_last_utc": "2026-03-07T12:56:00+00:00",
      "requested_start_utc": null,
      "requested_end_utc": null,
      "first_timestamp_utc": null,
      "last_timestamp_utc": null
    },
    {
      "symbol": "ETH/USDT",
      "status": "ok",
      "ohlcv_rows": 37187106,
      "ohlcv_start_ms": 1735689605000,
      "ohlcv_end_ms": 1772877628000,
      "feature_last_ts": 1772877600000,
      "requested_start_ms": 1772877600001,
      "requested_end_ms": 1772877628000,
      "upserted_rows": 1,
      "first_timestamp_ms": 1772877600000,
      "last_timestamp_ms": 1772877600000,
      "ohlcv_start_utc": "2025-01-01T00:00:05+00:00",
      "ohlcv_end_utc": "2026-03-07T10:00:28+00:00",
      "feature_last_utc": "2026-03-07T10:00:00+00:00",
      "requested_start_utc": "2026-03-07T10:00:00.001000+00:00",
      "requested_end_utc": "2026-03-07T10:00:28+00:00",
      "first_timestamp_utc": "2026-03-07T10:00:00+00:00",
      "last_timestamp_utc": "2026-03-07T10:00:00+00:00"
    },
    {
      "symbol": "XRP/USDT",
      "status": "ok",
      "ohlcv_rows": 37186932,
      "ohlcv_start_ms": 1735689605000,
      "ohlcv_end_ms": 1772877628000,
      "feature_last_ts": 1772877600000,
      "requested_start_ms": 1772877600001,
      "requested_end_ms": 1772877628000,
      "upserted_rows": 1,
      "first_timestamp_ms": 1772877600000,
      "last_timestamp_ms": 1772877600000,
      "ohlcv_start_utc": "2025-01-01T00:00:05+00:00",
      "ohlcv_end_utc": "2026-03-07T10:00:28+00:00",
      "feature_last_utc": "2026-03-07T10:00:00+00:00",
      "requested_start_utc": "2026-03-07T10:00:00.001000+00:00",
      "requested_end_utc": "2026-03-07T10:00:28+00:00",
      "first_timestamp_utc": "2026-03-07T10:00:00+00:00",
      "last_timestamp_utc": "2026-03-07T10:00:00+00:00"
    },
    {
      "symbol": "BNB/USDT",
      "status": "ok",
      "ohlcv_rows": 37186692,
      "ohlcv_start_ms": 1735689605000,
      "ohlcv_end_ms": 1772877627000,
      "feature_last_ts": 1772877600000,
      "requested_start_ms": 1772877600001,
      "requested_end_ms": 1772877627000,
      "upserted_rows": 1,
      "first_timestamp_ms": 1772877600000,
      "last_timestamp_ms": 1772877600000,
      "ohlcv_start_utc": "2025-01-01T00:00:05+00:00",
      "ohlcv_end_utc": "2026-03-07T10:00:27+00:00",
      "feature_last_utc": "2026-03-07T10:00:00+00:00",
      "requested_start_utc": "2026-03-07T10:00:00.001000+00:00",
      "requested_end_utc": "2026-03-07T10:00:27+00:00",
      "first_timestamp_utc": "2026-03-07T10:00:00+00:00",
      "last_timestamp_utc": "2026-03-07T10:00:00+00:00"
    },
    {
      "symbol": "SOL/USDT",
      "status": "ok",
      "ohlcv_rows": 37186939,
      "ohlcv_start_ms": 1735689605000,
      "ohlcv_end_ms": 1772877627000,
      "feature_last_ts": 1772877600000,
      "requested_start_ms": 1772877600001,
      "requested_end_ms": 1772877627000,
      "upserted_rows": 1,
      "first_timestamp_ms": 1772877600000,
      "last_timestamp_ms": 1772877600000,
      "ohlcv_start_utc": "2025-01-01T00:00:05+00:00",
      "ohlcv_end_utc": "2026-03-07T10:00:27+00:00",
      "feature_last_utc": "2026-03-07T10:00:00+00:00",
      "requested_start_utc": "2026-03-07T10:00:00.001000+00:00",
      "requested_end_utc": "2026-03-07T10:00:27+00:00",
      "first_timestamp_utc": "2026-03-07T10:00:00+00:00",
      "last_timestamp_utc": "2026-03-07T10:00:00+00:00"
    },
    {
      "symbol": "TRX/USDT",
      "status": "ok",
      "ohlcv_rows": 37186317,
      "ohlcv_start_ms": 1735689605000,
      "ohlcv_end_ms": 1772877627000,
      "feature_last_ts": 1772877600000,
      "requested_start_ms": 1772877600001,
      "requested_end_ms": 1772877627000,
      "upserted_rows": 1,
      "first_timestamp_ms": 1772877600000,
      "last_timestamp_ms": 1772877600000,
      "ohlcv_start_utc": "2025-01-01T00:00:05+00:00",
      "ohlcv_end_utc": "2026-03-07T10:00:27+00:00",
      "feature_last_utc": "2026-03-07T10:00:00+00:00",
      "requested_start_utc": "2026-03-07T10:00:00.001000+00:00",
      "requested_end_utc": "2026-03-07T10:00:27+00:00",
      "first_timestamp_utc": "2026-03-07T10:00:00+00:00",
      "last_timestamp_utc": "2026-03-07T10:00:00+00:00"
    },
    {
      "symbol": "DOGE/USDT",
      "status": "ok",
      "ohlcv_rows": 37186885,
      "ohlcv_start_ms": 1735689605000,
      "ohlcv_end_ms": 1772877627000,
      "feature_last_ts": 1772877600000,
      "requested_start_ms": 1772877600001,
      "requested_end_ms": 1772877627000,
      "upserted_rows": 1,
      "first_timestamp_ms": 1772877600000,
      "last_timestamp_ms": 1772877600000,
      "ohlcv_start_utc": "2025-01-01T00:00:05+00:00",
      "ohlcv_end_utc": "2026-03-07T10:00:27+00:00",
      "feature_last_utc": "2026-03-07T10:00:00+00:00",
      "requested_start_utc": "2026-03-07T10:00:00.001000+00:00",
      "requested_end_utc": "2026-03-07T10:00:27+00:00",
      "first_timestamp_utc": "2026-03-07T10:00:00+00:00",
      "last_timestamp_utc": "2026-03-07T10:00:00+00:00"
    },
    {
      "symbol": "ADA/USDT",
      "status": "ok",
      "ohlcv_rows": 37186744,
      "ohlcv_start_ms": 1735689605000,
      "ohlcv_end_ms": 1772877627000,
      "feature_last_ts": 1772877600000,
      "requested_start_ms": 1772877600001,
      "requested_end_ms": 1772877627000,
      "upserted_rows": 1,
      "first_timestamp_ms": 1772877600000,
      "last_timestamp_ms": 1772877600000,
      "ohlcv_start_utc": "2025-01-01T00:00:05+00:00",
      "ohlcv_end_utc": "2026-03-07T10:00:27+00:00",
      "feature_last_utc": "2026-03-07T10:00:00+00:00",
      "requested_start_utc": "2026-03-07T10:00:00.001000+00:00",
      "requested_end_utc": "2026-03-07T10:00:27+00:00",
      "first_timestamp_utc": "2026-03-07T10:00:00+00:00",
      "last_timestamp_utc": "2026-03-07T10:00:00+00:00"
    },
    {
      "symbol": "TON/USDT",
      "status": "up_to_date",
      "ohlcv_rows": 37185457,
      "ohlcv_start_ms": 1735689605000,
      "ohlcv_end_ms": 1772877625000,
      "feature_last_ts": 1772884800000,
      "ohlcv_start_utc": "2025-01-01T00:00:05+00:00",
      "ohlcv_end_utc": "2026-03-07T10:00:25+00:00",
      "feature_last_utc": "2026-03-07T12:00:00+00:00",
      "requested_start_utc": null,
      "requested_end_utc": null,
      "first_timestamp_utc": null,
      "last_timestamp_utc": null
    },
    {
      "symbol": "AVAX/USDT",
      "status": "ok",
      "ohlcv_rows": 37186663,
      "ohlcv_start_ms": 1735689605000,
      "ohlcv_end_ms": 1772877627000,
      "feature_last_ts": 1772877600000,
      "requested_start_ms": 1772877600001,
      "requested_end_ms": 1772877627000,
      "upserted_rows": 1,
      "first_timestamp_ms": 1772877600000,
      "last_timestamp_ms": 1772877600000,
      "ohlcv_start_utc": "2025-01-01T00:00:05+00:00",
      "ohlcv_end_utc": "2026-03-07T10:00:27+00:00",
      "feature_last_utc": "2026-03-07T10:00:00+00:00",
      "requested_start_utc": "2026-03-07T10:00:00.001000+00:00",
      "requested_end_utc": "2026-03-07T10:00:27+00:00",
      "first_timestamp_utc": "2026-03-07T10:00:00+00:00",
      "last_timestamp_utc": "2026-03-07T10:00:00+00:00"
    },
    {
      "symbol": "XAU/USDT",
      "status": "ok",
      "ohlcv_rows": 7436723,
      "ohlcv_start_ms": 1765440320000,
      "ohlcv_end_ms": 1772881366000,
      "feature_last_ts": 1772881320000,
      "requested_start_ms": 1772881320001,
      "requested_end_ms": 1772881366000,
      "upserted_rows": 0,
      "first_timestamp_ms": null,
      "last_timestamp_ms": null,
      "ohlcv_start_utc": "2025-12-11T08:05:20+00:00",
      "ohlcv_end_utc": "2026-03-07T11:02:46+00:00",
      "feature_last_utc": "2026-03-07T11:02:00+00:00",
      "requested_start_utc": "2026-03-07T11:02:00.001000+00:00",
      "requested_end_utc": "2026-03-07T11:02:46+00:00",
      "first_timestamp_utc": null,
      "last_timestamp_utc": null
    },
    {
      "symbol": "XAG/USDT",
      "status": "ok",
      "ohlcv_rows": 5101061,
      "ohlcv_start_ms": 1767780001000,
      "ohlcv_end_ms": 1772881366000,
      "feature_last_ts": 1772881320000,
      "requested_start_ms": 1772881320001,
      "requested_end_ms": 1772881366000,
      "upserted_rows": 0,
      "first_timestamp_ms": null,
      "last_timestamp_ms": null,
      "ohlcv_start_utc": "2026-01-07T10:00:01+00:00",
      "ohlcv_end_utc": "2026-03-07T11:02:46+00:00",
      "feature_last_utc": "2026-03-07T11:02:00+00:00",
      "requested_start_utc": "2026-03-07T11:02:00.001000+00:00",
      "requested_end_utc": "2026-03-07T11:02:46+00:00",
      "first_timestamp_utc": null,
      "last_timestamp_utc": null
    },
    {
      "symbol": "XPT/USDT",
      "status": "ok",
      "ohlcv_rows": 3112987,
      "ohlcv_start_ms": 1769767200000,
      "ohlcv_end_ms": 1772881346000,
      "feature_last_ts": 1772881320000,
      "requested_start_ms": 1772881320001,
      "requested_end_ms": 1772881346000,
      "upserted_rows": 0,
      "first_timestamp_ms": null,
      "last_timestamp_ms": null,
      "ohlcv_start_utc": "2026-01-30T10:00:00+00:00",
      "ohlcv_end_utc": "2026-03-07T11:02:26+00:00",
      "feature_last_utc": "2026-03-07T11:02:00+00:00",
      "requested_start_utc": "2026-03-07T11:02:00.001000+00:00",
      "requested_end_utc": "2026-03-07T11:02:26+00:00",
      "first_timestamp_utc": null,
      "last_timestamp_utc": null
    },
    {
      "symbol": "XPD/USDT",
      "status": "ok",
      "ohlcv_rows": 3112156,
      "ohlcv_start_ms": 1769768100000,
      "ohlcv_end_ms": 1772881356000,
      "feature_last_ts": 1772881320000,
      "requested_start_ms": 1772881320001,
      "requested_end_ms": 1772881356000,
      "upserted_rows": 0,
      "first_timestamp_ms": null,
      "last_timestamp_ms": null,
      "ohlcv_start_utc": "2026-01-30T10:15:00+00:00",
      "ohlcv_end_utc": "2026-03-07T11:02:36+00:00",
      "feature_last_utc": "2026-03-07T11:02:00+00:00",
      "requested_start_utc": "2026-03-07T11:02:00.001000+00:00",
      "requested_end_utc": "2026-03-07T11:02:36+00:00",
      "first_timestamp_utc": null,
      "last_timestamp_utc": null
    }
  ]
}