{
  "budget_bytes": 8589934592,
  "budget_mib": 8192.0,
  "error": null,
  "execution_profile": {
    "allow_metals": false,
    "custom_windows": false,
    "low_ram_profile": true,
    "requested_symbols": [
      "BTC/USDT",
      "ETH/USDT",
      "BNB/USDT",
      "SOL/USDT",
      "TRX/USDT"
    ],
    "requested_timeframes": [
      "5m"
    ],
    "requested_timeframes_raw": [
      "5m"
    ]
  },
  "generated_at": "2026-03-14T14:59:22.712476+00:00",
  "hard_limit_bytes": 6871947673,
  "hard_limit_mib": 6553.599999427795,
  "hard_trigger_count": 0,
  "label": "exact_window",
  "peak_rss_bytes": 2821373952,
  "peak_rss_mib": 2690.671875,
  "rss_log_path": "/home/hoky/Quants-agent/LuminaQuant/var/reports/exact_window_backtests/autonomous_intraday_5m_20260314T145221Z/5m/exact_window_rss_latest.jsonl",
  "sample_count": 19,
  "soft_limit_bytes": 5153960755,
  "soft_limit_mib": 4915.199999809265,
  "soft_trigger_count": 0,
  "status": "completed",
  "windows": {
    "actual_max_timestamp": "2026-03-07T10:00:00+00:00",
    "actual_oos_end_exclusive": "2026-03-07T10:00:00.001000+00:00",
    "requested_oos_end_exclusive": "2026-03-09T00:00:00+00:00",
    "train_end_exclusive": "2026-01-01T00:00:00+00:00",
    "train_start": "2025-01-01T00:00:00+00:00",
    "val_end_exclusive": "2026-02-01T00:00:00+00:00",
    "val_start": "2026-01-01T00:00:00+00:00"
  }
}