{
  "generated_at": "2026-03-17T11:17:53.906204+00:00",
  "source_report": "/home/hoky/Quants-agent/LuminaQuant/var/reports/exact_window_backtests/followup_status/autonomous_single_asset_zscore_reversion_15m_anchor_latest.json",
  "selection": {
    "fit_split": "val",
    "report_split": "oos",
    "selection_basis": "validation_only"
  },
  "cluster_count": 2,
  "clusters": [
    [
      "feecc2c87fbb8475",
      "4c8fdaeabe315563",
      "1d44f198202d7cdd"
    ],
    [
      "4b050c2ad437c77f"
    ]
  ],
  "constraints": {
    "max_strategy": 0.3,
    "max_family": 0.55,
    "max_asset": 0.2,
    "max_metals": 0.15,
    "family_caps": {
      "cross_sectional": 0.55,
      "market_neutral": 0.55,
      "mean_reversion": 0.55,
      "trend": 0.55
    },
    "configured": {
      "max_strategy": 0.3,
      "max_family": 0.55,
      "max_asset": 0.2,
      "max_metals": 0.15
    }
  },
  "scoring": {
    "candidate_rank_score_weights": {
      "sharpe_weight": 2.8,
      "deflated_sharpe_weight": 1.5,
      "pbo_penalty": 2.0,
      "return_weight": 25.0
    },
    "vol_targeting": {
      "target_vol_floor": 0.01,
      "vol_scale_cap": 2.0,
      "vol_scale_epsilon": 1e-12
    },
    "sensitivity": {
      "cost_stress_x2_multiplier": 2.0,
      "cost_stress_x3_multiplier": 3.0,
      "signal_drift_down_multiplier": 0.9,
      "signal_drift_up_multiplier": 1.1
    },
    "source": ""
  },
  "memory_policy": {
    "total_memory_cap_gib": 8.0,
    "heavy_run_cap_gib": 6.5,
    "disk_budget_gib": 30.0,
    "heavy_run_parallelism": 1,
    "light_worker_parallelism": 2,
    "exact_window_soft_fraction": 0.6,
    "exact_window_hard_fraction": 0.8,
    "rss_limit_fraction": 0.9,
    "total_memory_cap_bytes": 8589934592,
    "rss_limit_gib": 7.2,
    "heavy_lock_path": "/home/hoky/Quants-agent/LuminaQuant/var/reports/exact_window_backtests/followup_status/portfolio_followup_heavy_run.lock",
    "explicit_budget_bytes": 8589934592,
    "explicit_budget_gib": 8.0
  },
  "weights": [
    {
      "candidate_id": "feecc2c87fbb8475",
      "name": "composite_trend_stable_30m_stable_ls_highconv_ls_0.75_0.45_0.20_0.80",
      "strategy_class": "CompositeTrendStrategy",
      "family": "trend",
      "symbols": [
        "BTC/USDT",
        "ETH/USDT",
        "BNB/USDT",
        "SOL/USDT",
        "TRX/USDT"
      ],
      "timeframe": "30m",
      "weight": 0.30000000000000004,
      "fit_split": "val",
      "fit_sharpe": 4.427750205476359,
      "fit_return": 0.04987876459743679,
      "report_split": "oos",
      "report_sharpe": 2.2953624409038818,
      "report_return": 0.029547105294839504,
      "oos_sharpe": 2.2953624409038818,
      "oos_return": 0.029547105294839504
    },
    {
      "candidate_id": "4b050c2ad437c77f",
      "name": "pair_spread_1h_core_bnbusdt_trxusdt_2.2_0.55",
      "strategy_class": "PairSpreadZScoreStrategy",
      "family": "market_neutral",
      "symbols": [
        "BNB/USDT",
        "TRX/USDT"
      ],
      "timeframe": "1h",
      "weight": 0.30000000000000004,
      "fit_split": "val",
      "fit_sharpe": 3.8797484359521275,
      "fit_return": 0.01606720015631824,
      "report_split": "oos",
      "report_sharpe": 4.556884188045461,
      "report_return": 0.0723750581955176,
      "oos_sharpe": 4.556884188045461,
      "oos_return": 0.0723750581955176
    },
    {
      "candidate_id": "4c8fdaeabe315563",
      "name": "topcap_tsmom_1h_balanced_16_4_0.015",
      "strategy_class": "TopCapTimeSeriesMomentumStrategy",
      "family": "cross_sectional",
      "symbols": [
        "BTC/USDT",
        "ETH/USDT",
        "BNB/USDT",
        "SOL/USDT",
        "TRX/USDT"
      ],
      "timeframe": "1h",
      "weight": 0.2855156596930285,
      "fit_split": "val",
      "fit_sharpe": 1.640883072742277,
      "fit_return": 0.018372483665204387,
      "report_split": "oos",
      "report_sharpe": 1.4641557597854604,
      "report_return": 0.032378603658792526,
      "oos_sharpe": 1.4641557597854604,
      "oos_return": 0.032378603658792526
    },
    {
      "candidate_id": "1d44f198202d7cdd",
      "name": "mean_reversion_std_15m_balanced_ls_64_2.00",
      "strategy_class": "MeanReversionStdStrategy",
      "family": "mean_reversion",
      "symbols": [
        "BTC/USDT",
        "ETH/USDT",
        "XRP/USDT",
        "BNB/USDT",
        "SOL/USDT",
        "TRX/USDT",
        "DOGE/USDT",
        "ADA/USDT",
        "TON/USDT",
        "AVAX/USDT"
      ],
      "timeframe": "15m",
      "weight": 0.11448434030697151,
      "fit_split": "val",
      "fit_sharpe": -4.207548212367294,
      "fit_return": -0.11909244570583333,
      "report_split": "oos",
      "report_sharpe": -2.5103513541664833,
      "report_return": -0.11899194111519851,
      "oos_sharpe": -2.5103513541664833,
      "oos_return": -0.11899194111519851
    }
  ],
  "sleeve_budget": {
    "cross_sectional": 0.2855156596930285,
    "market_neutral": 0.30000000000000004,
    "mean_reversion": 0.11448434030697151,
    "trend": 0.30000000000000004
  },
  "portfolio_return_streams": {
    "train": [
      {
        "t": "2025-01-01T00:00:00Z",
        "v": -0.002012954779160298,
        "datetime": "2025-01-01T00:00:00Z"
      },
      {
        "t": "2025-01-02T00:00:00Z",
        "v": 0.0029442315806513394,
        "datetime": "2025-01-02T00:00:00Z"
      },
      {
        "t": "2025-01-03T00:00:00Z",
        "v": -0.0030604534172669244,
        "datetime": "2025-01-03T00:00:00Z"
      },
      {
        "t": "2025-01-04T00:00:00Z",
        "v": 0.0012380104625538293,
        "datetime": "2025-01-04T00:00:00Z"
      },
      {
        "t": "2025-01-05T00:00:00Z",
        "v": 7.2930614371889e-05,
        "datetime": "2025-01-05T00:00:00Z"
      },
      {
        "t": "2025-01-06T00:00:00Z",
        "v": 0.0020297444653461917,
        "datetime": "2025-01-06T00:00:00Z"
      },
      {
        "t": "2025-01-07T00:00:00Z",
        "v": 0.0009953788515620872,
        "datetime": "2025-01-07T00:00:00Z"
      },
      {
        "t": "2025-01-08T00:00:00Z",
        "v": -0.005499221544205331,
        "datetime": "2025-01-08T00:00:00Z"
      },
      {
        "t": "2025-01-09T00:00:00Z",
        "v": 0.0035345734623111994,
        "datetime": "2025-01-09T00:00:00Z"
      },
      {
        "t": "2025-01-10T00:00:00Z",
        "v": -0.0020140673275662593,
        "datetime": "2025-01-10T00:00:00Z"
      },
      {
        "t": "2025-01-11T00:00:00Z",
        "v": -0.0014401328096288308,
        "datetime": "2025-01-11T00:00:00Z"
      },
      {
        "t": "2025-01-12T00:00:00Z",
        "v": -0.0003327378028524212,
        "datetime": "2025-01-12T00:00:00Z"
      },
      {
        "t": "2025-01-13T00:00:00Z",
        "v": 0.0003733320815111278,
        "datetime": "2025-01-13T00:00:00Z"
      },
      {
        "t": "2025-01-14T00:00:00Z",
        "v": -0.0006880519420549467,
        "datetime": "2025-01-14T00:00:00Z"
      },
      {
        "t": "2025-01-15T00:00:00Z",
        "v": -0.0010406663446083445,
        "datetime": "2025-01-15T00:00:00Z"
      },
      {
        "t": "2025-01-16T00:00:00Z",
        "v": 7.234983836841092e-05,
        "datetime": "2025-01-16T00:00:00Z"
      },
      {
        "t": "2025-01-17T00:00:00Z",
        "v": -0.0010131546718619522,
        "datetime": "2025-01-17T00:00:00Z"
      },
      {
        "t": "2025-01-18T00:00:00Z",
        "v": 0.001790677108153337,
        "datetime": "2025-01-18T00:00:00Z"
      },
      {
        "t": "2025-01-19T00:00:00Z",
        "v": -0.0051831783018455365,
        "datetime": "2025-01-19T00:00:00Z"
      },
      {
        "t": "2025-01-20T00:00:00Z",
        "v": -0.0043019007443581446,
        "datetime": "2025-01-20T00:00:00Z"
      },
      {
        "t": "2025-01-21T00:00:00Z",
        "v": -0.0014132252426603585,
        "datetime": "2025-01-21T00:00:00Z"
      },
      {
        "t": "2025-01-22T00:00:00Z",
        "v": 0.0002960089815770376,
        "datetime": "2025-01-22T00:00:00Z"
      },
      {
        "t": "2025-01-23T00:00:00Z",
        "v": -0.003078931207722122,
        "datetime": "2025-01-23T00:00:00Z"
      },
      {
        "t": "2025-01-24T00:00:00Z",
        "v": -0.003269260458648821,
        "datetime": "2025-01-24T00:00:00Z"
      },
      {
        "t": "2025-01-25T00:00:00Z",
        "v": -0.000983410767636221,
        "datetime": "2025-01-25T00:00:00Z"
      },
      {
        "t": "2025-01-26T00:00:00Z",
        "v": -0.00034967232430249944,
        "datetime": "2025-01-26T00:00:00Z"
      },
      {
        "t": "2025-01-27T00:00:00Z",
        "v": 0.009671440685379857,
        "datetime": "2025-01-27T00:00:00Z"
      },
      {
        "t": "2025-01-28T00:00:00Z",
        "v": -0.0030394780906451853,
        "datetime": "2025-01-28T00:00:00Z"
      },
      {
        "t": "2025-01-29T00:00:00Z",
        "v": 0.004742057030721858,
        "datetime": "2025-01-29T00:00:00Z"
      },
      {
        "t": "2025-01-30T00:00:00Z",
        "v": 0.00511680826029216,
        "datetime": "2025-01-30T00:00:00Z"
      },
      {
        "t": "2025-01-31T00:00:00Z",
        "v": -0.0009746178321911002,
        "datetime": "2025-01-31T00:00:00Z"
      },
      {
        "t": "2025-02-01T00:00:00Z",
        "v": 0.008851683543026588,
        "datetime": "2025-02-01T00:00:00Z"
      },
      {
        "t": "2025-02-02T00:00:00Z",
        "v": -0.002385131461104779,
        "datetime": "2025-02-02T00:00:00Z"
      },
      {
        "t": "2025-02-03T00:00:00Z",
        "v": 0.006250836729677238,
        "datetime": "2025-02-03T00:00:00Z"
      },
      {
        "t": "2025-02-04T00:00:00Z",
        "v": 0.004846326752998063,
        "datetime": "2025-02-04T00:00:00Z"
      },
      {
        "t": "2025-02-05T00:00:00Z",
        "v": 0.0008442944960676945,
        "datetime": "2025-02-05T00:00:00Z"
      },
      {
        "t": "2025-02-06T00:00:00Z",
        "v": 0.0011202805048849468,
        "datetime": "2025-02-06T00:00:00Z"
      },
      {
        "t": "2025-02-07T00:00:00Z",
        "v": -0.0048867415535041,
        "datetime": "2025-02-07T00:00:00Z"
      },
      {
        "t": "2025-02-08T00:00:00Z",
        "v": 0.00042747001114665673,
        "datetime": "2025-02-08T00:00:00Z"
      },
      {
        "t": "2025-02-09T00:00:00Z",
        "v": 0.00023616037133350693,
        "datetime": "2025-02-09T00:00:00Z"
      },
      {
        "t": "2025-02-10T00:00:00Z",
        "v": 0.0034999383731562665,
        "datetime": "2025-02-10T00:00:00Z"
      },
      {
        "t": "2025-02-11T00:00:00Z",
        "v": 0.002243591780847747,
        "datetime": "2025-02-11T00:00:00Z"
      },
      {
        "t": "2025-02-12T00:00:00Z",
        "v": -0.0014079898056896403,
        "datetime": "2025-02-12T00:00:00Z"
      },
      {
        "t": "2025-02-13T00:00:00Z",
        "v": -9.700034142743586e-05,
        "datetime": "2025-02-13T00:00:00Z"
      },
      {
        "t": "2025-02-14T00:00:00Z",
        "v": 8.524681686326838e-05,
        "datetime": "2025-02-14T00:00:00Z"
      },
      {
        "t": "2025-02-15T00:00:00Z",
        "v": 0.0003091589153950071,
        "datetime": "2025-02-15T00:00:00Z"
      },
      {
        "t": "2025-02-16T00:00:00Z",
        "v": -0.0006944329632276085,
        "datetime": "2025-02-16T00:00:00Z"
      },
      {
        "t": "2025-02-17T00:00:00Z",
        "v": -0.00016604110771479327,
        "datetime": "2025-02-17T00:00:00Z"
      },
      {
        "t": "2025-02-18T00:00:00Z",
        "v": 0.006201808122094591,
        "datetime": "2025-02-18T00:00:00Z"
      },
      {
        "t": "2025-02-19T00:00:00Z",
        "v": -0.000233729046384634,
        "datetime": "2025-02-19T00:00:00Z"
      },
      {
        "t": "2025-02-20T00:00:00Z",
        "v": 0.0015511508005535196,
        "datetime": "2025-02-20T00:00:00Z"
      },
      {
        "t": "2025-02-21T00:00:00Z",
        "v": -0.002169652456646427,
        "datetime": "2025-02-21T00:00:00Z"
      },
      {
        "t": "2025-02-22T00:00:00Z",
        "v": -5.9378603030611245e-05,
        "datetime": "2025-02-22T00:00:00Z"
      },
      {
        "t": "2025-02-23T00:00:00Z",
        "v": -0.0003662830558600881,
        "datetime": "2025-02-23T00:00:00Z"
      },
      {
        "t": "2025-02-24T00:00:00Z",
        "v": 0.013982268316887045,
        "datetime": "2025-02-24T00:00:00Z"
      },
      {
        "t": "2025-02-25T00:00:00Z",
        "v": -6.023537748467596e-05,
        "datetime": "2025-02-25T00:00:00Z"
      },
      {
        "t": "2025-02-26T00:00:00Z",
        "v": 0.004826881852152879,
        "datetime": "2025-02-26T00:00:00Z"
      },
      {
        "t": "2025-02-27T00:00:00Z",
        "v": 0.0010462887526255724,
        "datetime": "2025-02-27T00:00:00Z"
      },
      {
        "t": "2025-02-28T00:00:00Z",
        "v": 0.006259002516638501,
        "datetime": "2025-02-28T00:00:00Z"
      },
      {
        "t": "2025-03-01T00:00:00Z",
        "v": -0.0069022206675206955,
        "datetime": "2025-03-01T00:00:00Z"
      },
      {
        "t": "2025-03-02T00:00:00Z",
        "v": 0.010148918220331699,
        "datetime": "2025-03-02T00:00:00Z"
      },
      {
        "t": "2025-03-03T00:00:00Z",
        "v": -0.013052180984102725,
        "datetime": "2025-03-03T00:00:00Z"
      },
      {
        "t": "2025-03-04T00:00:00Z",
        "v": -0.005968651238477424,
        "datetime": "2025-03-04T00:00:00Z"
      },
      {
        "t": "2025-03-05T00:00:00Z",
        "v": 0.0008830273679078682,
        "datetime": "2025-03-05T00:00:00Z"
      },
      {
        "t": "2025-03-06T00:00:00Z",
        "v": -0.00021508693563330203,
        "datetime": "2025-03-06T00:00:00Z"
      },
      {
        "t": "2025-03-07T00:00:00Z",
        "v": -2.0110886337599502e-05,
        "datetime": "2025-03-07T00:00:00Z"
      },
      {
        "t": "2025-03-08T00:00:00Z",
        "v": -0.0013309570422841558,
        "datetime": "2025-03-08T00:00:00Z"
      },
      {
        "t": "2025-03-09T00:00:00Z",
        "v": 0.0042846852112611335,
        "datetime": "2025-03-09T00:00:00Z"
      },
      {
        "t": "2025-03-10T00:00:00Z",
        "v": -0.0032831671464769625,
        "datetime": "2025-03-10T00:00:00Z"
      },
      {
        "t": "2025-03-11T00:00:00Z",
        "v": -0.004537992562962166,
        "datetime": "2025-03-11T00:00:00Z"
      },
      {
        "t": "2025-03-12T00:00:00Z",
        "v": -0.00120571580874919,
        "datetime": "2025-03-12T00:00:00Z"
      },
      {
        "t": "2025-03-13T00:00:00Z",
        "v": -4.617964793615268e-05,
        "datetime": "2025-03-13T00:00:00Z"
      },
      {
        "t": "2025-03-14T00:00:00Z",
        "v": 0.0024669869299561034,
        "datetime": "2025-03-14T00:00:00Z"
      },
      {
        "t": "2025-03-15T00:00:00Z",
        "v": 6.320479951400001e-05,
        "datetime": "2025-03-15T00:00:00Z"
      },
      {
        "t": "2025-03-16T00:00:00Z",
        "v": -0.0018452490120815972,
        "datetime": "2025-03-16T00:00:00Z"
      },
      {
        "t": "2025-03-17T00:00:00Z",
        "v": -0.00203058343153632,
        "datetime": "2025-03-17T00:00:00Z"
      },
      {
        "t": "2025-03-18T00:00:00Z",
        "v": 0.00033536102357438783,
        "datetime": "2025-03-18T00:00:00Z"
      },
      {
        "t": "2025-03-19T00:00:00Z",
        "v": 0.004601971453713325,
        "datetime": "2025-03-19T00:00:00Z"
      },
      {
        "t": "2025-03-20T00:00:00Z",
        "v": -0.0005857823548287219,
        "datetime": "2025-03-20T00:00:00Z"
      },
      {
        "t": "2025-03-21T00:00:00Z",
        "v": -0.0003530304562302189,
        "datetime": "2025-03-21T00:00:00Z"
      },
      {
        "t": "2025-03-22T00:00:00Z",
        "v": 0.0002068130566512384,
        "datetime": "2025-03-22T00:00:00Z"
      },
      {
        "t": "2025-03-23T00:00:00Z",
        "v": -0.0022038198049812953,
        "datetime": "2025-03-23T00:00:00Z"
      },
      {
        "t": "2025-03-24T00:00:00Z",
        "v": 0.0007647764012131946,
        "datetime": "2025-03-24T00:00:00Z"
      },
      {
        "t": "2025-03-25T00:00:00Z",
        "v": -0.004332378328059696,
        "datetime": "2025-03-25T00:00:00Z"
      },
      {
        "t": "2025-03-26T00:00:00Z",
        "v": -0.00024099823431191105,
        "datetime": "2025-03-26T00:00:00Z"
      },
      {
        "t": "2025-03-27T00:00:00Z",
        "v": -0.0018201466166104304,
        "datetime": "2025-03-27T00:00:00Z"
      },
      {
        "t": "2025-03-28T00:00:00Z",
        "v": -0.00031943777201868867,
        "datetime": "2025-03-28T00:00:00Z"
      },
      {
        "t": "2025-03-29T00:00:00Z",
        "v": 0.003193187248719336,
        "datetime": "2025-03-29T00:00:00Z"
      },
      {
        "t": "2025-03-30T00:00:00Z",
        "v": 0.0011375629285801112,
        "datetime": "2025-03-30T00:00:00Z"
      },
      {
        "t": "2025-03-31T00:00:00Z",
        "v": 0.0012284714690489924,
        "datetime": "2025-03-31T00:00:00Z"
      },
      {
        "t": "2025-04-01T00:00:00Z",
        "v": 0.0008933129328308977,
        "datetime": "2025-04-01T00:00:00Z"
      },
      {
        "t": "2025-04-02T00:00:00Z",
        "v": -0.010278216960624484,
        "datetime": "2025-04-02T00:00:00Z"
      },
      {
        "t": "2025-04-03T00:00:00Z",
        "v": 0.0005526244257299542,
        "datetime": "2025-04-03T00:00:00Z"
      },
      {
        "t": "2025-04-04T00:00:00Z",
        "v": -0.0008499441452180661,
        "datetime": "2025-04-04T00:00:00Z"
      },
      {
        "t": "2025-04-05T00:00:00Z",
        "v": -0.0033755489282262115,
        "datetime": "2025-04-05T00:00:00Z"
      },
      {
        "t": "2025-04-06T00:00:00Z",
        "v": 0.018047695864334905,
        "datetime": "2025-04-06T00:00:00Z"
      },
      {
        "t": "2025-04-07T00:00:00Z",
        "v": 0.0007537468392718632,
        "datetime": "2025-04-07T00:00:00Z"
      },
      {
        "t": "2025-04-08T00:00:00Z",
        "v": -0.0053266373995486255,
        "datetime": "2025-04-08T00:00:00Z"
      },
      {
        "t": "2025-04-09T00:00:00Z",
        "v": -0.0060497836180497845,
        "datetime": "2025-04-09T00:00:00Z"
      },
      {
        "t": "2025-04-10T00:00:00Z",
        "v": -0.0033403070059041377,
        "datetime": "2025-04-10T00:00:00Z"
      },
      {
        "t": "2025-04-11T00:00:00Z",
        "v": 0.001549083953379038,
        "datetime": "2025-04-11T00:00:00Z"
      },
      {
        "t": "2025-04-12T00:00:00Z",
        "v": 0.002625571627705723,
        "datetime": "2025-04-12T00:00:00Z"
      },
      {
        "t": "2025-04-13T00:00:00Z",
        "v": -0.009507270707445965,
        "datetime": "2025-04-13T00:00:00Z"
      },
      {
        "t": "2025-04-14T00:00:00Z",
        "v": 0.0018094286922578893,
        "datetime": "2025-04-14T00:00:00Z"
      },
      {
        "t": "2025-04-15T00:00:00Z",
        "v": 0.0009334064359253346,
        "datetime": "2025-04-15T00:00:00Z"
      },
      {
        "t": "2025-04-16T00:00:00Z",
        "v": 0.004251961308855117,
        "datetime": "2025-04-16T00:00:00Z"
      },
      {
        "t": "2025-04-17T00:00:00Z",
        "v": 0.001339543925234732,
        "datetime": "2025-04-17T00:00:00Z"
      },
      {
        "t": "2025-04-18T00:00:00Z",
        "v": 0.0009295602990618179,
        "datetime": "2025-04-18T00:00:00Z"
      },
      {
        "t": "2025-04-19T00:00:00Z",
        "v": -0.00046323198786687574,
        "datetime": "2025-04-19T00:00:00Z"
      },
      {
        "t": "2025-04-20T00:00:00Z",
        "v": -0.0021801234086365738,
        "datetime": "2025-04-20T00:00:00Z"
      },
      {
        "t": "2025-04-21T00:00:00Z",
        "v": -0.004645158521588776,
        "datetime": "2025-04-21T00:00:00Z"
      },
      {
        "t": "2025-04-22T00:00:00Z",
        "v": 0.006203886721134865,
        "datetime": "2025-04-22T00:00:00Z"
      },
      {
        "t": "2025-04-23T00:00:00Z",
        "v": -0.0007104277123943137,
        "datetime": "2025-04-23T00:00:00Z"
      },
      {
        "t": "2025-04-24T00:00:00Z",
        "v": -0.0013304494729529136,
        "datetime": "2025-04-24T00:00:00Z"
      },
      {
        "t": "2025-04-25T00:00:00Z",
        "v": 0.0014129499783752443,
        "datetime": "2025-04-25T00:00:00Z"
      },
      {
        "t": "2025-04-26T00:00:00Z",
        "v": 0.005025171260903197,
        "datetime": "2025-04-26T00:00:00Z"
      },
      {
        "t": "2025-04-27T00:00:00Z",
        "v": 0.0001086282387222717,
        "datetime": "2025-04-27T00:00:00Z"
      },
      {
        "t": "2025-04-28T00:00:00Z",
        "v": -0.0007698186025094785,
        "datetime": "2025-04-28T00:00:00Z"
      },
      {
        "t": "2025-04-29T00:00:00Z",
        "v": -0.00069617405445534,
        "datetime": "2025-04-29T00:00:00Z"
      },
      {
        "t": "2025-04-30T00:00:00Z",
        "v": -0.005173189476458499,
        "datetime": "2025-04-30T00:00:00Z"
      },
      {
        "t": "2025-05-01T00:00:00Z",
        "v": 0.0011601702949659634,
        "datetime": "2025-05-01T00:00:00Z"
      },
      {
        "t": "2025-05-02T00:00:00Z",
        "v": 0.001741124553156172,
        "datetime": "2025-05-02T00:00:00Z"
      },
      {
        "t": "2025-05-03T00:00:00Z",
        "v": 0.00013093010194954204,
        "datetime": "2025-05-03T00:00:00Z"
      },
      {
        "t": "2025-05-04T00:00:00Z",
        "v": -0.00026942564036864277,
        "datetime": "2025-05-04T00:00:00Z"
      },
      {
        "t": "2025-05-05T00:00:00Z",
        "v": -0.0016073124711626645,
        "datetime": "2025-05-05T00:00:00Z"
      },
      {
        "t": "2025-05-06T00:00:00Z",
        "v": -0.0006616989160987707,
        "datetime": "2025-05-06T00:00:00Z"
      },
      {
        "t": "2025-05-07T00:00:00Z",
        "v": -0.00027259610700005314,
        "datetime": "2025-05-07T00:00:00Z"
      },
      {
        "t": "2025-05-08T00:00:00Z",
        "v": 0.013688628437718571,
        "datetime": "2025-05-08T00:00:00Z"
      },
      {
        "t": "2025-05-09T00:00:00Z",
        "v": -0.00385620341033671,
        "datetime": "2025-05-09T00:00:00Z"
      },
      {
        "t": "2025-05-10T00:00:00Z",
        "v": 0.0011272530371002273,
        "datetime": "2025-05-10T00:00:00Z"
      },
      {
        "t": "2025-05-11T00:00:00Z",
        "v": 0.0010740744144734984,
        "datetime": "2025-05-11T00:00:00Z"
      },
      {
        "t": "2025-05-12T00:00:00Z",
        "v": -0.0016628715764630405,
        "datetime": "2025-05-12T00:00:00Z"
      },
      {
        "t": "2025-05-13T00:00:00Z",
        "v": 0.0013555267002990038,
        "datetime": "2025-05-13T00:00:00Z"
      },
      {
        "t": "2025-05-14T00:00:00Z",
        "v": -0.0007686554669743091,
        "datetime": "2025-05-14T00:00:00Z"
      },
      {
        "t": "2025-05-15T00:00:00Z",
        "v": 0.0018903782336493063,
        "datetime": "2025-05-15T00:00:00Z"
      },
      {
        "t": "2025-05-16T00:00:00Z",
        "v": -0.0006272930968925976,
        "datetime": "2025-05-16T00:00:00Z"
      },
      {
        "t": "2025-05-17T00:00:00Z",
        "v": 4.154162973595357e-05,
        "datetime": "2025-05-17T00:00:00Z"
      },
      {
        "t": "2025-05-18T00:00:00Z",
        "v": -0.005345040541846447,
        "datetime": "2025-05-18T00:00:00Z"
      },
      {
        "t": "2025-05-19T00:00:00Z",
        "v": -0.006864192073714881,
        "datetime": "2025-05-19T00:00:00Z"
      },
      {
        "t": "2025-05-20T00:00:00Z",
        "v": -0.00045039683781130833,
        "datetime": "2025-05-20T00:00:00Z"
      },
      {
        "t": "2025-05-21T00:00:00Z",
        "v": 0.0036577131363620457,
        "datetime": "2025-05-21T00:00:00Z"
      },
      {
        "t": "2025-05-22T00:00:00Z",
        "v": -0.0025137423102142248,
        "datetime": "2025-05-22T00:00:00Z"
      },
      {
        "t": "2025-05-23T00:00:00Z",
        "v": -0.0025662564820910483,
        "datetime": "2025-05-23T00:00:00Z"
      },
      {
        "t": "2025-05-24T00:00:00Z",
        "v": -0.0026679771007984123,
        "datetime": "2025-05-24T00:00:00Z"
      },
      {
        "t": "2025-05-25T00:00:00Z",
        "v": -0.0003800710524205636,
        "datetime": "2025-05-25T00:00:00Z"
      },
      {
        "t": "2025-05-26T00:00:00Z",
        "v": 0.00048169148629831316,
        "datetime": "2025-05-26T00:00:00Z"
      },
      {
        "t": "2025-05-27T00:00:00Z",
        "v": 0.0011861539037880777,
        "datetime": "2025-05-27T00:00:00Z"
      },
      {
        "t": "2025-05-28T00:00:00Z",
        "v": -0.00021990434812070955,
        "datetime": "2025-05-28T00:00:00Z"
      },
      {
        "t": "2025-05-29T00:00:00Z",
        "v": -0.002805726781629633,
        "datetime": "2025-05-29T00:00:00Z"
      },
      {
        "t": "2025-05-30T00:00:00Z",
        "v": -0.0018935631262595538,
        "datetime": "2025-05-30T00:00:00Z"
      },
      {
        "t": "2025-05-31T00:00:00Z",
        "v": -0.0007944035076512048,
        "datetime": "2025-05-31T00:00:00Z"
      },
      {
        "t": "2025-06-01T00:00:00Z",
        "v": 0.0013690531394475363,
        "datetime": "2025-06-01T00:00:00Z"
      },
      {
        "t": "2025-06-02T00:00:00Z",
        "v": -0.005977667244411518,
        "datetime": "2025-06-02T00:00:00Z"
      },
      {
        "t": "2025-06-03T00:00:00Z",
        "v": 0.0022309641762056675,
        "datetime": "2025-06-03T00:00:00Z"
      },
      {
        "t": "2025-06-04T00:00:00Z",
        "v": -0.0009686750106668883,
        "datetime": "2025-06-04T00:00:00Z"
      },
      {
        "t": "2025-06-05T00:00:00Z",
        "v": 0.008019070934700069,
        "datetime": "2025-06-05T00:00:00Z"
      },
      {
        "t": "2025-06-06T00:00:00Z",
        "v": -0.004862759136594152,
        "datetime": "2025-06-06T00:00:00Z"
      },
      {
        "t": "2025-06-07T00:00:00Z",
        "v": -0.0008612256872832993,
        "datetime": "2025-06-07T00:00:00Z"
      },
      {
        "t": "2025-06-08T00:00:00Z",
        "v": -0.0012826872868640722,
        "datetime": "2025-06-08T00:00:00Z"
      },
      {
        "t": "2025-06-09T00:00:00Z",
        "v": 0.0041467409161788,
        "datetime": "2025-06-09T00:00:00Z"
      },
      {
        "t": "2025-06-10T00:00:00Z",
        "v": 0.0016078198660389857,
        "datetime": "2025-06-10T00:00:00Z"
      },
      {
        "t": "2025-06-11T00:00:00Z",
        "v": -0.0005062616784802717,
        "datetime": "2025-06-11T00:00:00Z"
      },
      {
        "t": "2025-06-12T00:00:00Z",
        "v": 0.006956755475542515,
        "datetime": "2025-06-12T00:00:00Z"
      },
      {
        "t": "2025-06-13T00:00:00Z",
        "v": 0.005019912769378265,
        "datetime": "2025-06-13T00:00:00Z"
      },
      {
        "t": "2025-06-14T00:00:00Z",
        "v": 0.001224667880109894,
        "datetime": "2025-06-14T00:00:00Z"
      },
      {
        "t": "2025-06-15T00:00:00Z",
        "v": 0.002272891790068926,
        "datetime": "2025-06-15T00:00:00Z"
      },
      {
        "t": "2025-06-16T00:00:00Z",
        "v": -0.0018326918247187907,
        "datetime": "2025-06-16T00:00:00Z"
      },
      {
        "t": "2025-06-17T00:00:00Z",
        "v": -0.0011421344347840744,
        "datetime": "2025-06-17T00:00:00Z"
      },
      {
        "t": "2025-06-18T00:00:00Z",
        "v": -0.0021628117531512854,
        "datetime": "2025-06-18T00:00:00Z"
      },
      {
        "t": "2025-06-19T00:00:00Z",
        "v": -0.0016593523894975375,
        "datetime": "2025-06-19T00:00:00Z"
      },
      {
        "t": "2025-06-20T00:00:00Z",
        "v": -0.003984210369620711,
        "datetime": "2025-06-20T00:00:00Z"
      },
      {
        "t": "2025-06-21T00:00:00Z",
        "v": -0.003874608472592604,
        "datetime": "2025-06-21T00:00:00Z"
      },
      {
        "t": "2025-06-22T00:00:00Z",
        "v": 0.002299468021992824,
        "datetime": "2025-06-22T00:00:00Z"
      },
      {
        "t": "2025-06-23T00:00:00Z",
        "v": -0.004524441610668174,
        "datetime": "2025-06-23T00:00:00Z"
      },
      {
        "t": "2025-06-24T00:00:00Z",
        "v": 0.00015485227451222843,
        "datetime": "2025-06-24T00:00:00Z"
      },
      {
        "t": "2025-06-25T00:00:00Z",
        "v": -0.0016108466880950289,
        "datetime": "2025-06-25T00:00:00Z"
      },
      {
        "t": "2025-06-26T00:00:00Z",
        "v": -0.002317716183221365,
        "datetime": "2025-06-26T00:00:00Z"
      },
      {
        "t": "2025-06-27T00:00:00Z",
        "v": -0.0022670549307121195,
        "datetime": "2025-06-27T00:00:00Z"
      },
      {
        "t": "2025-06-28T00:00:00Z",
        "v": -0.0006017117025721653,
        "datetime": "2025-06-28T00:00:00Z"
      },
      {
        "t": "2025-06-29T00:00:00Z",
        "v": -0.0011821510091577156,
        "datetime": "2025-06-29T00:00:00Z"
      },
      {
        "t": "2025-06-30T00:00:00Z",
        "v": -0.0020286012782286104,
        "datetime": "2025-06-30T00:00:00Z"
      },
      {
        "t": "2025-07-01T00:00:00Z",
        "v": -0.0003305770091256478,
        "datetime": "2025-07-01T00:00:00Z"
      },
      {
        "t": "2025-07-02T00:00:00Z",
        "v": -0.00253911712653933,
        "datetime": "2025-07-02T00:00:00Z"
      },
      {
        "t": "2025-07-03T00:00:00Z",
        "v": 0.0022265438784972733,
        "datetime": "2025-07-03T00:00:00Z"
      },
      {
        "t": "2025-07-04T00:00:00Z",
        "v": -0.0031503746674074193,
        "datetime": "2025-07-04T00:00:00Z"
      },
      {
        "t": "2025-07-05T00:00:00Z",
        "v": 0.001073281517983405,
        "datetime": "2025-07-05T00:00:00Z"
      },
      {
        "t": "2025-07-06T00:00:00Z",
        "v": -0.0029845559292178848,
        "datetime": "2025-07-06T00:00:00Z"
      },
      {
        "t": "2025-07-07T00:00:00Z",
        "v": 0.0004921232323384854,
        "datetime": "2025-07-07T00:00:00Z"
      },
      {
        "t": "2025-07-08T00:00:00Z",
        "v": -0.0015404198482139163,
        "datetime": "2025-07-08T00:00:00Z"
      },
      {
        "t": "2025-07-09T00:00:00Z",
        "v": -0.00040406536640791237,
        "datetime": "2025-07-09T00:00:00Z"
      },
      {
        "t": "2025-07-10T00:00:00Z",
        "v": -0.0014273881787094929,
        "datetime": "2025-07-10T00:00:00Z"
      },
      {
        "t": "2025-07-11T00:00:00Z",
        "v": 0.002077011117748496,
        "datetime": "2025-07-11T00:00:00Z"
      },
      {
        "t": "2025-07-12T00:00:00Z",
        "v": 0.0010444612463089988,
        "datetime": "2025-07-12T00:00:00Z"
      },
      {
        "t": "2025-07-13T00:00:00Z",
        "v": -0.00026847653794240955,
        "datetime": "2025-07-13T00:00:00Z"
      },
      {
        "t": "2025-07-14T00:00:00Z",
        "v": -0.0023862798389603208,
        "datetime": "2025-07-14T00:00:00Z"
      },
      {
        "t": "2025-07-15T00:00:00Z",
        "v": -0.0026034956397956764,
        "datetime": "2025-07-15T00:00:00Z"
      },
      {
        "t": "2025-07-16T00:00:00Z",
        "v": 0.007683309631978043,
        "datetime": "2025-07-16T00:00:00Z"
      },
      {
        "t": "2025-07-17T00:00:00Z",
        "v": 0.0023288163587258785,
        "datetime": "2025-07-17T00:00:00Z"
      },
      {
        "t": "2025-07-18T00:00:00Z",
        "v": -0.007547403980442452,
        "datetime": "2025-07-18T00:00:00Z"
      },
      {
        "t": "2025-07-19T00:00:00Z",
        "v": 0.0014349846827830409,
        "datetime": "2025-07-19T00:00:00Z"
      },
      {
        "t": "2025-07-20T00:00:00Z",
        "v": -0.0022716747797039867,
        "datetime": "2025-07-20T00:00:00Z"
      },
      {
        "t": "2025-07-21T00:00:00Z",
        "v": 0.0008975550277939542,
        "datetime": "2025-07-21T00:00:00Z"
      },
      {
        "t": "2025-07-22T00:00:00Z",
        "v": 0.004782270735898752,
        "datetime": "2025-07-22T00:00:00Z"
      },
      {
        "t": "2025-07-23T00:00:00Z",
        "v": -0.007389585185257043,
        "datetime": "2025-07-23T00:00:00Z"
      },
      {
        "t": "2025-07-24T00:00:00Z",
        "v": 0.0028989069115142037,
        "datetime": "2025-07-24T00:00:00Z"
      },
      {
        "t": "2025-07-25T00:00:00Z",
        "v": -0.0014360697238722624,
        "datetime": "2025-07-25T00:00:00Z"
      },
      {
        "t": "2025-07-26T00:00:00Z",
        "v": -0.0008080429801684643,
        "datetime": "2025-07-26T00:00:00Z"
      },
      {
        "t": "2025-07-27T00:00:00Z",
        "v": 0.004035636709209418,
        "datetime": "2025-07-27T00:00:00Z"
      },
      {
        "t": "2025-07-28T00:00:00Z",
        "v": -0.00415644303794492,
        "datetime": "2025-07-28T00:00:00Z"
      },
      {
        "t": "2025-07-29T00:00:00Z",
        "v": 0.008644889254937626,
        "datetime": "2025-07-29T00:00:00Z"
      },
      {
        "t": "2025-07-30T00:00:00Z",
        "v": 0.0009867504525825968,
        "datetime": "2025-07-30T00:00:00Z"
      },
      {
        "t": "2025-07-31T00:00:00Z",
        "v": -0.0024071705252392984,
        "datetime": "2025-07-31T00:00:00Z"
      },
      {
        "t": "2025-08-01T00:00:00Z",
        "v": 0.0016055957778539505,
        "datetime": "2025-08-01T00:00:00Z"
      },
      {
        "t": "2025-08-02T00:00:00Z",
        "v": -0.004574851931273361,
        "datetime": "2025-08-02T00:00:00Z"
      },
      {
        "t": "2025-08-03T00:00:00Z",
        "v": -0.0005975212701925045,
        "datetime": "2025-08-03T00:00:00Z"
      },
      {
        "t": "2025-08-04T00:00:00Z",
        "v": 0.0026619055926883606,
        "datetime": "2025-08-04T00:00:00Z"
      },
      {
        "t": "2025-08-05T00:00:00Z",
        "v": -0.004259689466147726,
        "datetime": "2025-08-05T00:00:00Z"
      },
      {
        "t": "2025-08-06T00:00:00Z",
        "v": -0.005873084879992569,
        "datetime": "2025-08-06T00:00:00Z"
      },
      {
        "t": "2025-08-07T00:00:00Z",
        "v": -0.00024322251494711357,
        "datetime": "2025-08-07T00:00:00Z"
      },
      {
        "t": "2025-08-08T00:00:00Z",
        "v": -0.001551974394845587,
        "datetime": "2025-08-08T00:00:00Z"
      },
      {
        "t": "2025-08-09T00:00:00Z",
        "v": -0.00012888703409647635,
        "datetime": "2025-08-09T00:00:00Z"
      },
      {
        "t": "2025-08-10T00:00:00Z",
        "v": -0.0018847592512167624,
        "datetime": "2025-08-10T00:00:00Z"
      },
      {
        "t": "2025-08-11T00:00:00Z",
        "v": 0.0004522897396181984,
        "datetime": "2025-08-11T00:00:00Z"
      },
      {
        "t": "2025-08-12T00:00:00Z",
        "v": 0.002151780778027244,
        "datetime": "2025-08-12T00:00:00Z"
      },
      {
        "t": "2025-08-13T00:00:00Z",
        "v": 0.003409614881573402,
        "datetime": "2025-08-13T00:00:00Z"
      },
      {
        "t": "2025-08-14T00:00:00Z",
        "v": -0.004960311766097187,
        "datetime": "2025-08-14T00:00:00Z"
      },
      {
        "t": "2025-08-15T00:00:00Z",
        "v": -0.0023895160872688622,
        "datetime": "2025-08-15T00:00:00Z"
      },
      {
        "t": "2025-08-16T00:00:00Z",
        "v": 0.0030165109805968516,
        "datetime": "2025-08-16T00:00:00Z"
      },
      {
        "t": "2025-08-17T00:00:00Z",
        "v": -0.0022763581970262916,
        "datetime": "2025-08-17T00:00:00Z"
      },
      {
        "t": "2025-08-18T00:00:00Z",
        "v": -0.0031723677110422916,
        "datetime": "2025-08-18T00:00:00Z"
      },
      {
        "t": "2025-08-19T00:00:00Z",
        "v": -0.0013123358098310078,
        "datetime": "2025-08-19T00:00:00Z"
      },
      {
        "t": "2025-08-20T00:00:00Z",
        "v": -0.0029312106434057424,
        "datetime": "2025-08-20T00:00:00Z"
      },
      {
        "t": "2025-08-21T00:00:00Z",
        "v": -0.001718087815629635,
        "datetime": "2025-08-21T00:00:00Z"
      },
      {
        "t": "2025-08-22T00:00:00Z",
        "v": 0.00530324929562773,
        "datetime": "2025-08-22T00:00:00Z"
      },
      {
        "t": "2025-08-23T00:00:00Z",
        "v": 0.0005876895310535956,
        "datetime": "2025-08-23T00:00:00Z"
      },
      {
        "t": "2025-08-24T00:00:00Z",
        "v": 0.0006069861409727502,
        "datetime": "2025-08-24T00:00:00Z"
      },
      {
        "t": "2025-08-25T00:00:00Z",
        "v": 0.005029038119647242,
        "datetime": "2025-08-25T00:00:00Z"
      },
      {
        "t": "2025-08-26T00:00:00Z",
        "v": -0.003114780285121159,
        "datetime": "2025-08-26T00:00:00Z"
      },
      {
        "t": "2025-08-27T00:00:00Z",
        "v": 0.001476948329340334,
        "datetime": "2025-08-27T00:00:00Z"
      },
      {
        "t": "2025-08-28T00:00:00Z",
        "v": 0.00022489294286076014,
        "datetime": "2025-08-28T00:00:00Z"
      },
      {
        "t": "2025-08-29T00:00:00Z",
        "v": 0.0014583640443921334,
        "datetime": "2025-08-29T00:00:00Z"
      },
      {
        "t": "2025-08-30T00:00:00Z",
        "v": 0.00044091350320278556,
        "datetime": "2025-08-30T00:00:00Z"
      },
      {
        "t": "2025-08-31T00:00:00Z",
        "v": -0.0031219964864967874,
        "datetime": "2025-08-31T00:00:00Z"
      },
      {
        "t": "2025-09-01T00:00:00Z",
        "v": -0.0017563199931675101,
        "datetime": "2025-09-01T00:00:00Z"
      },
      {
        "t": "2025-09-02T00:00:00Z",
        "v": 0.0027903474779498788,
        "datetime": "2025-09-02T00:00:00Z"
      },
      {
        "t": "2025-09-03T00:00:00Z",
        "v": 0.0015467070056068436,
        "datetime": "2025-09-03T00:00:00Z"
      },
      {
        "t": "2025-09-04T00:00:00Z",
        "v": -0.0007714296183684053,
        "datetime": "2025-09-04T00:00:00Z"
      },
      {
        "t": "2025-09-05T00:00:00Z",
        "v": -0.0043878327117487905,
        "datetime": "2025-09-05T00:00:00Z"
      },
      {
        "t": "2025-09-06T00:00:00Z",
        "v": 0.0034089634647170184,
        "datetime": "2025-09-06T00:00:00Z"
      },
      {
        "t": "2025-09-07T00:00:00Z",
        "v": -0.004956310118349057,
        "datetime": "2025-09-07T00:00:00Z"
      },
      {
        "t": "2025-09-08T00:00:00Z",
        "v": -0.0020719339497222372,
        "datetime": "2025-09-08T00:00:00Z"
      },
      {
        "t": "2025-09-09T00:00:00Z",
        "v": 0.00025484452823904577,
        "datetime": "2025-09-09T00:00:00Z"
      },
      {
        "t": "2025-09-10T00:00:00Z",
        "v": -0.0035490280598043447,
        "datetime": "2025-09-10T00:00:00Z"
      },
      {
        "t": "2025-09-11T00:00:00Z",
        "v": 0.00034237490344173245,
        "datetime": "2025-09-11T00:00:00Z"
      },
      {
        "t": "2025-09-12T00:00:00Z",
        "v": 0.0033220740658918024,
        "datetime": "2025-09-12T00:00:00Z"
      },
      {
        "t": "2025-09-13T00:00:00Z",
        "v": -0.0027624248446600254,
        "datetime": "2025-09-13T00:00:00Z"
      },
      {
        "t": "2025-09-14T00:00:00Z",
        "v": 0.0011377611017464634,
        "datetime": "2025-09-14T00:00:00Z"
      },
      {
        "t": "2025-09-15T00:00:00Z",
        "v": -0.002743191662472408,
        "datetime": "2025-09-15T00:00:00Z"
      },
      {
        "t": "2025-09-16T00:00:00Z",
        "v": -0.0058096828344405185,
        "datetime": "2025-09-16T00:00:00Z"
      },
      {
        "t": "2025-09-17T00:00:00Z",
        "v": -0.001381053160127817,
        "datetime": "2025-09-17T00:00:00Z"
      },
      {
        "t": "2025-09-18T00:00:00Z",
        "v": -0.00014960514225613767,
        "datetime": "2025-09-18T00:00:00Z"
      },
      {
        "t": "2025-09-19T00:00:00Z",
        "v": -0.001349263140128731,
        "datetime": "2025-09-19T00:00:00Z"
      },
      {
        "t": "2025-09-20T00:00:00Z",
        "v": 0.0006255013041685555,
        "datetime": "2025-09-20T00:00:00Z"
      },
      {
        "t": "2025-09-21T00:00:00Z",
        "v": 0.0006231760862125183,
        "datetime": "2025-09-21T00:00:00Z"
      },
      {
        "t": "2025-09-22T00:00:00Z",
        "v": 0.0027685729501168736,
        "datetime": "2025-09-22T00:00:00Z"
      },
      {
        "t": "2025-09-23T00:00:00Z",
        "v": -0.0013785308340514251,
        "datetime": "2025-09-23T00:00:00Z"
      },
      {
        "t": "2025-09-24T00:00:00Z",
        "v": 0.001203922254356151,
        "datetime": "2025-09-24T00:00:00Z"
      },
      {
        "t": "2025-09-25T00:00:00Z",
        "v": 0.0007706400293251503,
        "datetime": "2025-09-25T00:00:00Z"
      },
      {
        "t": "2025-09-26T00:00:00Z",
        "v": 0.00027175718423237086,
        "datetime": "2025-09-26T00:00:00Z"
      },
      {
        "t": "2025-09-27T00:00:00Z",
        "v": 0.0006238944196959408,
        "datetime": "2025-09-27T00:00:00Z"
      },
      {
        "t": "2025-09-28T00:00:00Z",
        "v": -0.0033857981568059057,
        "datetime": "2025-09-28T00:00:00Z"
      },
      {
        "t": "2025-09-29T00:00:00Z",
        "v": -0.0035586243939061254,
        "datetime": "2025-09-29T00:00:00Z"
      },
      {
        "t": "2025-09-30T00:00:00Z",
        "v": -0.0007805422391010238,
        "datetime": "2025-09-30T00:00:00Z"
      },
      {
        "t": "2025-10-01T00:00:00Z",
        "v": 0.0019507821736879252,
        "datetime": "2025-10-01T00:00:00Z"
      },
      {
        "t": "2025-10-02T00:00:00Z",
        "v": 0.005535423574499488,
        "datetime": "2025-10-02T00:00:00Z"
      },
      {
        "t": "2025-10-03T00:00:00Z",
        "v": 0.0033489050161462967,
        "datetime": "2025-10-03T00:00:00Z"
      },
      {
        "t": "2025-10-04T00:00:00Z",
        "v": -0.001672152655298091,
        "datetime": "2025-10-04T00:00:00Z"
      },
      {
        "t": "2025-10-05T00:00:00Z",
        "v": -0.0056116115613869064,
        "datetime": "2025-10-05T00:00:00Z"
      },
      {
        "t": "2025-10-06T00:00:00Z",
        "v": 0.0005687755476950108,
        "datetime": "2025-10-06T00:00:00Z"
      },
      {
        "t": "2025-10-07T00:00:00Z",
        "v": -0.00211859433316123,
        "datetime": "2025-10-07T00:00:00Z"
      },
      {
        "t": "2025-10-08T00:00:00Z",
        "v": -0.0016630575497199995,
        "datetime": "2025-10-08T00:00:00Z"
      },
      {
        "t": "2025-10-09T00:00:00Z",
        "v": -0.0023734466325444955,
        "datetime": "2025-10-09T00:00:00Z"
      },
      {
        "t": "2025-10-10T00:00:00Z",
        "v": 0.001575455110826865,
        "datetime": "2025-10-10T00:00:00Z"
      },
      {
        "t": "2025-10-11T00:00:00Z",
        "v": 0.002536174908581458,
        "datetime": "2025-10-11T00:00:00Z"
      },
      {
        "t": "2025-10-12T00:00:00Z",
        "v": -0.005807711973890655,
        "datetime": "2025-10-12T00:00:00Z"
      },
      {
        "t": "2025-10-13T00:00:00Z",
        "v": -0.00029074898615656956,
        "datetime": "2025-10-13T00:00:00Z"
      },
      {
        "t": "2025-10-14T00:00:00Z",
        "v": -0.007656422893709139,
        "datetime": "2025-10-14T00:00:00Z"
      },
      {
        "t": "2025-10-15T00:00:00Z",
        "v": -0.0005094925253211507,
        "datetime": "2025-10-15T00:00:00Z"
      },
      {
        "t": "2025-10-16T00:00:00Z",
        "v": -0.0032039280376188767,
        "datetime": "2025-10-16T00:00:00Z"
      },
      {
        "t": "2025-10-17T00:00:00Z",
        "v": 0.007118443410728441,
        "datetime": "2025-10-17T00:00:00Z"
      },
      {
        "t": "2025-10-18T00:00:00Z",
        "v": -0.0006329502187020548,
        "datetime": "2025-10-18T00:00:00Z"
      },
      {
        "t": "2025-10-19T00:00:00Z",
        "v": 0.0009160907383531169,
        "datetime": "2025-10-19T00:00:00Z"
      },
      {
        "t": "2025-10-20T00:00:00Z",
        "v": 0.002684685894986524,
        "datetime": "2025-10-20T00:00:00Z"
      },
      {
        "t": "2025-10-21T00:00:00Z",
        "v": -0.010235434915761062,
        "datetime": "2025-10-21T00:00:00Z"
      },
      {
        "t": "2025-10-22T00:00:00Z",
        "v": 0.0001372308701966294,
        "datetime": "2025-10-22T00:00:00Z"
      },
      {
        "t": "2025-10-23T00:00:00Z",
        "v": 0.0011209226403161455,
        "datetime": "2025-10-23T00:00:00Z"
      },
      {
        "t": "2025-10-24T00:00:00Z",
        "v": -0.0011117477508117285,
        "datetime": "2025-10-24T00:00:00Z"
      },
      {
        "t": "2025-10-25T00:00:00Z",
        "v": -7.512134746619746e-05,
        "datetime": "2025-10-25T00:00:00Z"
      },
      {
        "t": "2025-10-26T00:00:00Z",
        "v": 0.0004793478067074233,
        "datetime": "2025-10-26T00:00:00Z"
      },
      {
        "t": "2025-10-27T00:00:00Z",
        "v": -0.001007350591937501,
        "datetime": "2025-10-27T00:00:00Z"
      },
      {
        "t": "2025-10-28T00:00:00Z",
        "v": -0.0015452422077488392,
        "datetime": "2025-10-28T00:00:00Z"
      },
      {
        "t": "2025-10-29T00:00:00Z",
        "v": 0.0047952732509895174,
        "datetime": "2025-10-29T00:00:00Z"
      },
      {
        "t": "2025-10-30T00:00:00Z",
        "v": -0.004059518364727191,
        "datetime": "2025-10-30T00:00:00Z"
      },
      {
        "t": "2025-10-31T00:00:00Z",
        "v": -0.00135293238524948,
        "datetime": "2025-10-31T00:00:00Z"
      },
      {
        "t": "2025-11-01T00:00:00Z",
        "v": 0.0005756861047949921,
        "datetime": "2025-11-01T00:00:00Z"
      },
      {
        "t": "2025-11-02T00:00:00Z",
        "v": 0.002215380029884161,
        "datetime": "2025-11-02T00:00:00Z"
      },
      {
        "t": "2025-11-03T00:00:00Z",
        "v": 0.006465454816169178,
        "datetime": "2025-11-03T00:00:00Z"
      },
      {
        "t": "2025-11-04T00:00:00Z",
        "v": 0.015636447636807313,
        "datetime": "2025-11-04T00:00:00Z"
      },
      {
        "t": "2025-11-05T00:00:00Z",
        "v": -0.0026922008993187415,
        "datetime": "2025-11-05T00:00:00Z"
      },
      {
        "t": "2025-11-06T00:00:00Z",
        "v": -0.003505959195246219,
        "datetime": "2025-11-06T00:00:00Z"
      },
      {
        "t": "2025-11-07T00:00:00Z",
        "v": -0.005488548546307655,
        "datetime": "2025-11-07T00:00:00Z"
      },
      {
        "t": "2025-11-08T00:00:00Z",
        "v": -0.0014920281628315868,
        "datetime": "2025-11-08T00:00:00Z"
      },
      {
        "t": "2025-11-09T00:00:00Z",
        "v": 0.00028176673391910336,
        "datetime": "2025-11-09T00:00:00Z"
      },
      {
        "t": "2025-11-10T00:00:00Z",
        "v": 0.001960837390412552,
        "datetime": "2025-11-10T00:00:00Z"
      },
      {
        "t": "2025-11-11T00:00:00Z",
        "v": 0.004038580439977203,
        "datetime": "2025-11-11T00:00:00Z"
      },
      {
        "t": "2025-11-12T00:00:00Z",
        "v": -0.006930518800603876,
        "datetime": "2025-11-12T00:00:00Z"
      },
      {
        "t": "2025-11-13T00:00:00Z",
        "v": -0.00019574806320883675,
        "datetime": "2025-11-13T00:00:00Z"
      },
      {
        "t": "2025-11-14T00:00:00Z",
        "v": -0.000873884870650341,
        "datetime": "2025-11-14T00:00:00Z"
      },
      {
        "t": "2025-11-15T00:00:00Z",
        "v": -0.0005893632594417119,
        "datetime": "2025-11-15T00:00:00Z"
      },
      {
        "t": "2025-11-16T00:00:00Z",
        "v": -0.0019149415145119023,
        "datetime": "2025-11-16T00:00:00Z"
      },
      {
        "t": "2025-11-17T00:00:00Z",
        "v": -0.008225003806990514,
        "datetime": "2025-11-17T00:00:00Z"
      },
      {
        "t": "2025-11-18T00:00:00Z",
        "v": -0.008190476330586383,
        "datetime": "2025-11-18T00:00:00Z"
      },
      {
        "t": "2025-11-19T00:00:00Z",
        "v": 0.0026377809514086656,
        "datetime": "2025-11-19T00:00:00Z"
      },
      {
        "t": "2025-11-20T00:00:00Z",
        "v": -0.0022919241699322396,
        "datetime": "2025-11-20T00:00:00Z"
      },
      {
        "t": "2025-11-21T00:00:00Z",
        "v": 0.002987848603423773,
        "datetime": "2025-11-21T00:00:00Z"
      },
      {
        "t": "2025-11-22T00:00:00Z",
        "v": 0.0016276335401339405,
        "datetime": "2025-11-22T00:00:00Z"
      },
      {
        "t": "2025-11-23T00:00:00Z",
        "v": -0.0011524928269113389,
        "datetime": "2025-11-23T00:00:00Z"
      },
      {
        "t": "2025-11-24T00:00:00Z",
        "v": 0.0021815205118924648,
        "datetime": "2025-11-24T00:00:00Z"
      },
      {
        "t": "2025-11-25T00:00:00Z",
        "v": -0.002417985002679841,
        "datetime": "2025-11-25T00:00:00Z"
      },
      {
        "t": "2025-11-26T00:00:00Z",
        "v": -0.007627540347799239,
        "datetime": "2025-11-26T00:00:00Z"
      },
      {
        "t": "2025-11-27T00:00:00Z",
        "v": -0.0006518962717907097,
        "datetime": "2025-11-27T00:00:00Z"
      },
      {
        "t": "2025-11-28T00:00:00Z",
        "v": -0.0005030031367393782,
        "datetime": "2025-11-28T00:00:00Z"
      },
      {
        "t": "2025-11-29T00:00:00Z",
        "v": -0.0003471125046204693,
        "datetime": "2025-11-29T00:00:00Z"
      },
      {
        "t": "2025-11-30T00:00:00Z",
        "v": -0.002845731011338074,
        "datetime": "2025-11-30T00:00:00Z"
      },
      {
        "t": "2025-12-01T00:00:00Z",
        "v": 0.0021188649494216566,
        "datetime": "2025-12-01T00:00:00Z"
      },
      {
        "t": "2025-12-02T00:00:00Z",
        "v": -0.004917248487176324,
        "datetime": "2025-12-02T00:00:00Z"
      },
      {
        "t": "2025-12-03T00:00:00Z",
        "v": 0.0038643100691254997,
        "datetime": "2025-12-03T00:00:00Z"
      },
      {
        "t": "2025-12-04T00:00:00Z",
        "v": -0.0006435485951559709,
        "datetime": "2025-12-04T00:00:00Z"
      },
      {
        "t": "2025-12-05T00:00:00Z",
        "v": 0.001309922502100493,
        "datetime": "2025-12-05T00:00:00Z"
      },
      {
        "t": "2025-12-06T00:00:00Z",
        "v": 0.0002054305652682487,
        "datetime": "2025-12-06T00:00:00Z"
      },
      {
        "t": "2025-12-07T00:00:00Z",
        "v": -0.002626732100338943,
        "datetime": "2025-12-07T00:00:00Z"
      },
      {
        "t": "2025-12-08T00:00:00Z",
        "v": 0.0012926868021175134,
        "datetime": "2025-12-08T00:00:00Z"
      },
      {
        "t": "2025-12-09T00:00:00Z",
        "v": -0.002579335898062341,
        "datetime": "2025-12-09T00:00:00Z"
      },
      {
        "t": "2025-12-10T00:00:00Z",
        "v": 0.0005262488033471005,
        "datetime": "2025-12-10T00:00:00Z"
      },
      {
        "t": "2025-12-11T00:00:00Z",
        "v": -0.00611529310747395,
        "datetime": "2025-12-11T00:00:00Z"
      },
      {
        "t": "2025-12-12T00:00:00Z",
        "v": -0.003975996430053284,
        "datetime": "2025-12-12T00:00:00Z"
      },
      {
        "t": "2025-12-13T00:00:00Z",
        "v": 0.00033888517772992315,
        "datetime": "2025-12-13T00:00:00Z"
      },
      {
        "t": "2025-12-14T00:00:00Z",
        "v": -0.001233472794649748,
        "datetime": "2025-12-14T00:00:00Z"
      },
      {
        "t": "2025-12-15T00:00:00Z",
        "v": -0.001747241495089531,
        "datetime": "2025-12-15T00:00:00Z"
      },
      {
        "t": "2025-12-16T00:00:00Z",
        "v": 0.00035130937192968264,
        "datetime": "2025-12-16T00:00:00Z"
      },
      {
        "t": "2025-12-17T00:00:00Z",
        "v": 0.0001317806617921885,
        "datetime": "2025-12-17T00:00:00Z"
      },
      {
        "t": "2025-12-18T00:00:00Z",
        "v": -0.010013499489035259,
        "datetime": "2025-12-18T00:00:00Z"
      },
      {
        "t": "2025-12-19T00:00:00Z",
        "v": -0.00023873729637149472,
        "datetime": "2025-12-19T00:00:00Z"
      },
      {
        "t": "2025-12-20T00:00:00Z",
        "v": 0.0006991557225933254,
        "datetime": "2025-12-20T00:00:00Z"
      },
      {
        "t": "2025-12-21T00:00:00Z",
        "v": 0.00046045059549196585,
        "datetime": "2025-12-21T00:00:00Z"
      },
      {
        "t": "2025-12-22T00:00:00Z",
        "v": -0.0005369560358345735,
        "datetime": "2025-12-22T00:00:00Z"
      },
      {
        "t": "2025-12-23T00:00:00Z",
        "v": -0.0034202856351601635,
        "datetime": "2025-12-23T00:00:00Z"
      },
      {
        "t": "2025-12-24T00:00:00Z",
        "v": -0.001808962807681826,
        "datetime": "2025-12-24T00:00:00Z"
      },
      {
        "t": "2025-12-25T00:00:00Z",
        "v": 0.0019458494072171228,
        "datetime": "2025-12-25T00:00:00Z"
      },
      {
        "t": "2025-12-26T00:00:00Z",
        "v": -0.001350454011684918,
        "datetime": "2025-12-26T00:00:00Z"
      },
      {
        "t": "2025-12-27T00:00:00Z",
        "v": -0.00011390533600642893,
        "datetime": "2025-12-27T00:00:00Z"
      },
      {
        "t": "2025-12-28T00:00:00Z",
        "v": -0.0024317286846202457,
        "datetime": "2025-12-28T00:00:00Z"
      },
      {
        "t": "2025-12-29T00:00:00Z",
        "v": -0.0025184846629139426,
        "datetime": "2025-12-29T00:00:00Z"
      },
      {
        "t": "2025-12-30T00:00:00Z",
        "v": -0.002130948582593166,
        "datetime": "2025-12-30T00:00:00Z"
      },
      {
        "t": "2025-12-31T00:00:00Z",
        "v": -0.002872084796079112,
        "datetime": "2025-12-31T00:00:00Z"
      }
    ],
    "val": [
      {
        "t": "2026-01-01T00:00:00Z",
        "v": -0.0022251802382747634,
        "datetime": "2026-01-01T00:00:00Z"
      },
      {
        "t": "2026-01-02T00:00:00Z",
        "v": 0.0003404456300346026,
        "datetime": "2026-01-02T00:00:00Z"
      },
      {
        "t": "2026-01-03T00:00:00Z",
        "v": -6.32707609615629e-05,
        "datetime": "2026-01-03T00:00:00Z"
      },
      {
        "t": "2026-01-04T00:00:00Z",
        "v": -0.00103632459711423,
        "datetime": "2026-01-04T00:00:00Z"
      },
      {
        "t": "2026-01-05T00:00:00Z",
        "v": -0.001156746649726792,
        "datetime": "2026-01-05T00:00:00Z"
      },
      {
        "t": "2026-01-06T00:00:00Z",
        "v": -0.0021473639593456626,
        "datetime": "2026-01-06T00:00:00Z"
      },
      {
        "t": "2026-01-07T00:00:00Z",
        "v": -0.0008889916669737979,
        "datetime": "2026-01-07T00:00:00Z"
      },
      {
        "t": "2026-01-08T00:00:00Z",
        "v": -0.00011419024056485332,
        "datetime": "2026-01-08T00:00:00Z"
      },
      {
        "t": "2026-01-09T00:00:00Z",
        "v": 0.0010804428740519463,
        "datetime": "2026-01-09T00:00:00Z"
      },
      {
        "t": "2026-01-10T00:00:00Z",
        "v": 7.95314529599859e-06,
        "datetime": "2026-01-10T00:00:00Z"
      },
      {
        "t": "2026-01-11T00:00:00Z",
        "v": 0.0003483447093343966,
        "datetime": "2026-01-11T00:00:00Z"
      },
      {
        "t": "2026-01-12T00:00:00Z",
        "v": -0.000539846126389805,
        "datetime": "2026-01-12T00:00:00Z"
      },
      {
        "t": "2026-01-13T00:00:00Z",
        "v": -0.0026727147502862213,
        "datetime": "2026-01-13T00:00:00Z"
      },
      {
        "t": "2026-01-14T00:00:00Z",
        "v": 0.0010394314266234197,
        "datetime": "2026-01-14T00:00:00Z"
      },
      {
        "t": "2026-01-15T00:00:00Z",
        "v": 0.0031216771714058433,
        "datetime": "2026-01-15T00:00:00Z"
      },
      {
        "t": "2026-01-16T00:00:00Z",
        "v": -0.004158432338932048,
        "datetime": "2026-01-16T00:00:00Z"
      },
      {
        "t": "2026-01-17T00:00:00Z",
        "v": -0.0007637938052123625,
        "datetime": "2026-01-17T00:00:00Z"
      },
      {
        "t": "2026-01-18T00:00:00Z",
        "v": -0.0003671022594260011,
        "datetime": "2026-01-18T00:00:00Z"
      },
      {
        "t": "2026-01-19T00:00:00Z",
        "v": 0.0017028823667412896,
        "datetime": "2026-01-19T00:00:00Z"
      },
      {
        "t": "2026-01-20T00:00:00Z",
        "v": 0.007113714409877941,
        "datetime": "2026-01-20T00:00:00Z"
      },
      {
        "t": "2026-01-21T00:00:00Z",
        "v": -0.00021849057144840336,
        "datetime": "2026-01-21T00:00:00Z"
      },
      {
        "t": "2026-01-22T00:00:00Z",
        "v": -0.002358553684986671,
        "datetime": "2026-01-22T00:00:00Z"
      },
      {
        "t": "2026-01-23T00:00:00Z",
        "v": 0.0037557591724174826,
        "datetime": "2026-01-23T00:00:00Z"
      },
      {
        "t": "2026-01-24T00:00:00Z",
        "v": 0.0004545427049647845,
        "datetime": "2026-01-24T00:00:00Z"
      },
      {
        "t": "2026-01-25T00:00:00Z",
        "v": 0.0009406317336817156,
        "datetime": "2026-01-25T00:00:00Z"
      },
      {
        "t": "2026-01-26T00:00:00Z",
        "v": -0.0038937826092247277,
        "datetime": "2026-01-26T00:00:00Z"
      },
      {
        "t": "2026-01-27T00:00:00Z",
        "v": 0.0026492637463558593,
        "datetime": "2026-01-27T00:00:00Z"
      },
      {
        "t": "2026-01-28T00:00:00Z",
        "v": 0.000564151799741844,
        "datetime": "2026-01-28T00:00:00Z"
      },
      {
        "t": "2026-01-29T00:00:00Z",
        "v": 0.005083217194158228,
        "datetime": "2026-01-29T00:00:00Z"
      },
      {
        "t": "2026-01-30T00:00:00Z",
        "v": 0.001754802699841941,
        "datetime": "2026-01-30T00:00:00Z"
      },
      {
        "t": "2026-01-31T00:00:00Z",
        "v": 0.004163864758933407,
        "datetime": "2026-01-31T00:00:00Z"
      }
    ],
    "oos": [
      {
        "t": "2026-02-01T00:00:00Z",
        "v": -0.0014497838680605616,
        "datetime": "2026-02-01T00:00:00Z"
      },
      {
        "t": "2026-02-02T00:00:00Z",
        "v": -0.003945999678471032,
        "datetime": "2026-02-02T00:00:00Z"
      },
      {
        "t": "2026-02-03T00:00:00Z",
        "v": 0.004122439071411632,
        "datetime": "2026-02-03T00:00:00Z"
      },
      {
        "t": "2026-02-04T00:00:00Z",
        "v": 0.011111841738141112,
        "datetime": "2026-02-04T00:00:00Z"
      },
      {
        "t": "2026-02-05T00:00:00Z",
        "v": 0.02889832215447658,
        "datetime": "2026-02-05T00:00:00Z"
      },
      {
        "t": "2026-02-06T00:00:00Z",
        "v": -0.008195851133411638,
        "datetime": "2026-02-06T00:00:00Z"
      },
      {
        "t": "2026-02-07T00:00:00Z",
        "v": -0.0013108229544069783,
        "datetime": "2026-02-07T00:00:00Z"
      },
      {
        "t": "2026-02-08T00:00:00Z",
        "v": 0.0005397737308531169,
        "datetime": "2026-02-08T00:00:00Z"
      },
      {
        "t": "2026-02-09T00:00:00Z",
        "v": -0.00470444551771798,
        "datetime": "2026-02-09T00:00:00Z"
      },
      {
        "t": "2026-02-10T00:00:00Z",
        "v": 0.00012072432513471695,
        "datetime": "2026-02-10T00:00:00Z"
      },
      {
        "t": "2026-02-11T00:00:00Z",
        "v": 0.000716303815358157,
        "datetime": "2026-02-11T00:00:00Z"
      },
      {
        "t": "2026-02-12T00:00:00Z",
        "v": -0.004174953325689293,
        "datetime": "2026-02-12T00:00:00Z"
      },
      {
        "t": "2026-02-13T00:00:00Z",
        "v": 9.889895243240469e-05,
        "datetime": "2026-02-13T00:00:00Z"
      },
      {
        "t": "2026-02-14T00:00:00Z",
        "v": 0.002876957896926201,
        "datetime": "2026-02-14T00:00:00Z"
      },
      {
        "t": "2026-02-15T00:00:00Z",
        "v": 0.000938354019451193,
        "datetime": "2026-02-15T00:00:00Z"
      },
      {
        "t": "2026-02-16T00:00:00Z",
        "v": -5.5201312711312955e-05,
        "datetime": "2026-02-16T00:00:00Z"
      },
      {
        "t": "2026-02-17T00:00:00Z",
        "v": 0.0003790984357530474,
        "datetime": "2026-02-17T00:00:00Z"
      },
      {
        "t": "2026-02-18T00:00:00Z",
        "v": -0.0021677557323163785,
        "datetime": "2026-02-18T00:00:00Z"
      },
      {
        "t": "2026-02-19T00:00:00Z",
        "v": -0.000904981423805301,
        "datetime": "2026-02-19T00:00:00Z"
      },
      {
        "t": "2026-02-20T00:00:00Z",
        "v": 0.0033198973930222524,
        "datetime": "2026-02-20T00:00:00Z"
      },
      {
        "t": "2026-02-21T00:00:00Z",
        "v": -0.0010881656196481703,
        "datetime": "2026-02-21T00:00:00Z"
      },
      {
        "t": "2026-02-22T00:00:00Z",
        "v": -0.0017497974938781719,
        "datetime": "2026-02-22T00:00:00Z"
      },
      {
        "t": "2026-02-23T00:00:00Z",
        "v": 0.009350197573643365,
        "datetime": "2026-02-23T00:00:00Z"
      },
      {
        "t": "2026-02-24T00:00:00Z",
        "v": -0.0005839400991502593,
        "datetime": "2026-02-24T00:00:00Z"
      },
      {
        "t": "2026-02-25T00:00:00Z",
        "v": 0.005814412307553549,
        "datetime": "2026-02-25T00:00:00Z"
      },
      {
        "t": "2026-02-26T00:00:00Z",
        "v": -0.0006406877264602392,
        "datetime": "2026-02-26T00:00:00Z"
      },
      {
        "t": "2026-02-27T00:00:00Z",
        "v": 0.00016917753315442839,
        "datetime": "2026-02-27T00:00:00Z"
      },
      {
        "t": "2026-02-28T00:00:00Z",
        "v": -0.003082505995484841,
        "datetime": "2026-02-28T00:00:00Z"
      },
      {
        "t": "2026-03-01T00:00:00Z",
        "v": -0.0016657387862764493,
        "datetime": "2026-03-01T00:00:00Z"
      },
      {
        "t": "2026-03-02T00:00:00Z",
        "v": -0.003712549674152082,
        "datetime": "2026-03-02T00:00:00Z"
      },
      {
        "t": "2026-03-03T00:00:00Z",
        "v": -0.00260461049539707,
        "datetime": "2026-03-03T00:00:00Z"
      },
      {
        "t": "2026-03-04T00:00:00Z",
        "v": 0.0009750955746670011,
        "datetime": "2026-03-04T00:00:00Z"
      },
      {
        "t": "2026-03-05T00:00:00Z",
        "v": -0.0007052322248056133,
        "datetime": "2026-03-05T00:00:00Z"
      },
      {
        "t": "2026-03-06T00:00:00Z",
        "v": 0.001484012168179376,
        "datetime": "2026-03-06T00:00:00Z"
      },
      {
        "t": "2026-03-07T00:00:00Z",
        "v": -0.0008984792029326755,
        "datetime": "2026-03-07T00:00:00Z"
      }
    ]
  },
  "portfolio_metrics": {
    "train": {
      "total_return": -0.11203915823777533,
      "cagr": -0.11203915823777533,
      "sharpe": -1.66866052524752,
      "sortino": -2.6422459842400987,
      "calmar": -0.7372503974597537,
      "max_drawdown": 0.1519689356883548,
      "volatility": 0.0697481562970797
    },
    "val": {
      "total_return": 0.01148519586438601,
      "cagr": 0.14391689831783205,
      "sharpe": 2.825831801746726,
      "sortino": 5.318179669353386,
      "calmar": 17.34143608264216,
      "max_drawdown": 0.008299018468365782,
      "volatility": 0.04798432488807756
    },
    "oos": {
      "total_return": 0.02699435733005795,
      "cagr": 0.3201956981323759,
      "sharpe": 2.4352730379440595,
      "sortino": 7.519913905364839,
      "calmar": 18.924785647105068,
      "max_drawdown": 0.016919383083282447,
      "volatility": 0.11679548816973509
    }
  },
  "fit_metrics": {
    "total_return": 0.01148519586438601,
    "cagr": 0.14391689831783205,
    "sharpe": 2.825831801746726,
    "sortino": 5.318179669353386,
    "calmar": 17.34143608264216,
    "max_drawdown": 0.008299018468365782,
    "volatility": 0.04798432488807756
  },
  "report_metrics": {
    "total_return": 0.02699435733005795,
    "cagr": 0.3201956981323759,
    "sharpe": 2.4352730379440595,
    "sortino": 7.519913905364839,
    "calmar": 18.924785647105068,
    "max_drawdown": 0.016919383083282447,
    "volatility": 0.11679548816973509
  },
  "sensitivity": {
    "cost_stress": {
      "x2": {
        "total_return": 0.026425226662259327,
        "cagr": 0.31258590684897936,
        "sharpe": 2.3857414288455923,
        "sortino": 7.366964552166596,
        "calmar": 18.35640125986332,
        "max_drawdown": 0.017028713985047572,
        "volatility": 0.11679548816973509
      },
      "x3": {
        "total_return": 0.02585640238349729,
        "cagr": 0.30501985997089887,
        "sharpe": 2.336209819747124,
        "sortino": 7.2140151989683545,
        "calmar": 17.797832102585105,
        "max_drawdown": 0.017138034464691643,
        "volatility": 0.11679548816973509
      }
    },
    "param_drift": {
      "minus_10pct_signal": {
        "total_return": 0.024320541274639895,
        "cagr": 0.2847876117937671,
        "sharpe": 2.4352730379440604,
        "sortino": 7.519913905364842,
        "calmar": 18.692341333572948,
        "max_drawdown": 0.015235523828267872,
        "volatility": 0.10511593935276158
      },
      "plus_10pct_signal": {
        "total_return": 0.02966235859066213,
        "cagr": 0.3564038360133932,
        "sharpe": 2.43527303794406,
        "sortino": 7.519913905364839,
        "calmar": 19.16000295851923,
        "max_drawdown": 0.0186014499467978,
        "volatility": 0.1284750369867086
      }
    }
  }
}