{
  "budget_bytes": 15720022016,
  "budget_mib": 14991.78125,
  "error": null,
  "execution_profile": {
    "allow_metals": false,
    "custom_windows": false,
    "low_ram_profile": true,
    "requested_symbols": [
      "BTC/USDT",
      "ETH/USDT",
      "BNB/USDT",
      "SOL/USDT",
      "TRX/USDT"
    ],
    "requested_timeframes": [
      "1h"
    ],
    "requested_timeframes_raw": [
      "1h"
    ]
  },
  "generated_at": "2026-03-15T07:06:26.504678+00:00",
  "hard_limit_bytes": 12576017612,
  "hard_limit_mib": 11993.42499923706,
  "hard_trigger_count": 0,
  "label": "exact_window",
  "peak_rss_bytes": 3367149568,
  "peak_rss_mib": 3211.1640625,
  "rss_log_path": "/home/hoky/Quants-agent/LuminaQuant/var/reports/exact_window_backtests/autonomous_residual_topcap_1h_retry_20260315T0612Z/1h/exact_window_rss_latest.jsonl",
  "sample_count": 39,
  "soft_limit_bytes": 9432013209,
  "soft_limit_mib": 8995.068749427795,
  "soft_trigger_count": 0,
  "status": "completed",
  "windows": {
    "actual_max_timestamp": "2026-03-07T10:00:00+00:00",
    "actual_oos_end_exclusive": "2026-03-07T10:00:00.001000+00:00",
    "requested_oos_end_exclusive": "2026-03-09T00:00:00+00:00",
    "train_end_exclusive": "2026-01-01T00:00:00+00:00",
    "train_start": "2025-01-01T00:00:00+00:00",
    "val_end_exclusive": "2026-02-01T00:00:00+00:00",
    "val_start": "2026-01-01T00:00:00+00:00"
  }
}